Workbook

Sheet Cover
B2: Dataset information | F2: Dataset format information
C3: Column name | D3: Dataset entries
A4: 1 | B4: Identification | C4: dataset_id | D4: auto | F4: IEDC data file
A5: 2 | C5: dataset_name | D5: 4_UPI_CIRCOMOD_D4.1
A6: 3 | C6: dataset_version | D6: V1.0 | F6: Format_Version | G6: IEDC_V1
A7: 4 | B7: Grouping | C7: datagroup_id | D7: CIRCOMOD_Task4.2_Process_Descriptions | F7: Dataset_Unit | G7: LIST
A8: 5 | C8: data_category | D8: 4 | F8: Dataset_Uncertainty | G8: LIST
A9: 6 | C9: data_type | D9: Unit process inventory | F9: Dataset_Comment | G9: LIST
A10: 7 | C10: data_layer | D10: Misc. physical units | F10: Dataset_RecordType | G10: LIST | H10: No_Rows | I10: 4386
A11: 8 | B11: System location: What elements and objects in the system are described? | C11: process_scope | D11: Material production processes | F11: Aspects_classifications | G11: Aspects_Attribute_No | H11: DATA | I11: DATA_Info
A12: 9 | C12: process_resolution | D12: project-wide material and waste production/treatment processes | F12: process | G12: 1 | H12: value
A13: 10 | C13: product_scope | D13: none | F13: material | G13: 1 | H13: unit nominator
A14: 11 | C14: product_resolution | D14: none | F14: material_category | G14: 1 | H14: unit denominator
A15: 12 | C15: material_scope | D15: Materials and waste | F15: layer | G15: 1 | H15: stats_array_string
A16: 13 | C16: material_resolution | D16: project-wide material and waste groups | H16: comment
A17: 14 | C17: regional_scope | D17: Global
A18: 15 | C18: regional_resolution | D18: process specific
A19: 16 | C19: temporal_scope | D19: 1970-2100
A20: 17 | C20: temporal_resolution | D20: process specific
A21: 18 | B21: Description | C21: description | D21: Unit process inventory for various material production and waste treatment processes studied by the CIRCOMOD models
A22: 19 | C22: keywords | D22: material production; recycling; unit process;
A23: 20 | C23: data_provenance | D23: Result of academic MFA work
A24: 21 | C24: dataset_size | D24: 4386
A25: 22 | C25: comment
A26: 23 | B26: System location: Dataset aspects and semantics. For aspects: [Aspect;symbol;classification]. Mandatory aspects in gray shading. | C26: aspect_1 | D26: process
A27: 24 | C27: aspect_1_classification | D27: 82
A28: 25 | C28: aspect_2 | D28: material
A29: 26 | C29: aspect_2_classification | D29: 83
A30: 27 | C30: aspect_3 | D30: material_category
A31: 28 | C31: aspect_3_classification | D31: 84
A32: 29 | C32: aspect_4 | D32: layer
A33: 30 | C33: aspect_4_classification | D33: 20
A34: 31 | C34: aspect_5 | D34: none
A35: 32 | C35: aspect_5_classification | D35: none
A36: 33 | C36: aspect_6 | D36: none
A37: 34 | C37: aspect_6_classification | D37: none
A38: 35 | C38: aspect_7 | D38: none
A39: 36 | C39: aspect_7_classification | D39: none
A40: 37 | C40: aspect_8 | D40: none
A41: 38 | C41: aspect_8_classification | D41: none
A42: 39 | C42: aspect_9 | D42: none
A43: 40 | C43: aspect_9_classification | D43: none
A44: 41 | C44: aspect_10 | D44: none
A45: 42 | C45: aspect_10_classification | D45: none
... A52: 49 | C52: semantic_string_general | D52: UPI flow of [aspect2] in category [aspect3] for process [aspect1] on layer [aspect 4] has [value].
A53: 50 | B53: Data access and licence | C53: type_of_source | D53: Proprietary report or research article
A54: 51 | C54: project_license | D54: miscellaneous licenses, see the comments in the dataset
A55: 52 | C55: main_author | D55: See the log and ref sheets of parameter file
A56: 53 | C56: dataset_link | D56: See the log and ref sheets of parameter file
A57: 54 | C57: dataset_format | D57: See the log and ref sheets of parameter file
A58: 55 | C58: project_report | D58: See the log and ref sheets of parameter file
A59: 56 | C59: suggested_citation | D59: See the log and ref sheets of parameter file
A60: 57 | C60: visible | D60: 1
A61: 58 | B61: Data submission, review, and conversion info | C61: access_date | D61: See the log and ref sheets of parameter file
A62: 59 | C62: submission_date | D62: 45138
A63: 60 | C63: submitting_user | D63: CIRCOMOD team via Marianne Zanon Zotin
A64: 61 | C64: dataset_conversion_info | D64: Numbers manually copied from original sources to Excel spreadsheet
A65: 62 | C65: review_date
A66: 63 | C66: review_user
A67: 64 | C67: review_comment
A68: 65 | B68: Reserve | C68: reserve1
A69: 66 | C69: reserve2
A70: 67 | C70: reserve3
A71: 68 | C71: reserve4
A72: 69 | C72: reserve5

Sheet Data
A1: process | B1: material | C1: material_category | D1: layer | E1: value | F1: unit nominator | G1: unit denominator | H1: stats_array string | I1: comment | J1: link to log entry | K1: Data source | L1: material_group
A2: [a] Beneficiation, sulfide ore (Crushing, grinding, flotation) | B2: copper concentrate, sulfide ore | C2: reference_product | D2: mass | E2: 1 | F2: t | G2: 1 | H2: none | J2: [PU] Sulf_Ore_Conc | K2: See log sheet | L2: 2603
A3: [a] Beneficiation, sulfide ore (Crushing, grinding, flotation) | B3: sulphide ore | C3: from environment (natural resource) | D3: mass | E3: 4 | F3: t | G3: t | H3: none | J3: [PU] Sulf_Ore_Conc | K3: See log sheet
A4: [a] Beneficiation, sulfide ore (Crushing, grinding, flotation) | B4: electricity | C4: from technosphere (energy_carrier) | D4: energy | E4: 16.4 | F4: kWh | G4: t | H4: none | J4: [PU] Sulf_Ore_Conc | K4: See log sheet
A5: [a] Beneficiation, sulfide ore (Crushing, grinding, flotation) | B5: water | C5: from environment (natural resource) | D5: volume | E5: 0.6 | F5: m3 | G5: t | H5: none | J5: [PU] Sulf_Ore_Conc | K5: See log sheet
A6: [a] Beneficiation, sulfide ore (Crushing, grinding, flotation) | B6: steel | C6: from technosphere (material) | D6: mass | E6: 0.7 | F6: t | G6: t | H6: none | J6: [PU] Sulf_Ore_Conc | K6: See log sheet
A7: [a] Beneficiation, sulfide ore (Crushing, grinding, flotation) | B7: quicklime | C7: from technosphere (material) | D7: mass | E7: 1 | F7: t | G7: t | H7: none | J7: [PU] Sulf_Ore_Conc | K7: See log sheet
A8: [a] Beneficiation, sulfide ore (Crushing, grinding, flotation) | B8: other chemicals | C8: from technosphere (material) | D8: mass | E8: 0.13 | F8: t | G8: t | H8: none | J8: [PU] Sulf_Ore_Conc | K8: See log sheet
A9: [a] Beneficiation, sulfide ore (Crushing, grinding, flotation) | B9: water | C9: to environment (emission) | D9: volume | E9: 0.6 | F9: m3 | G9: t | H9: none | J9: [PU] Sulf_Ore_Conc | K9: See log sheet
A10: [a] Beneficiation, sulfide ore (Crushing, grinding, flotation) | B10: tailings | C10: to technosphere (waste) | D10: mass | E10: 5.83 | F10: t | G10: t | H10: none | J10: [PU] Sulf_Ore_Conc | K10: See log sheet
A11: [a] Calcined clay, flash calciner | B11: metakaolin | C11: reference_product | D11: mass | E11: 1 | F11: t | G11: 1 | H11: none | J11: [a] Calcined clay, flash calciner | K11: Martinez et al. 2023 [117] | L11: 2507
A12: [a] Calcined clay, flash calciner | B12: kaolinite, dry | C12: from environment (natural resource) | D12: mass | E12: 1.16 | F12: t | G12: 1 | H12: none | J12: [a] Calcined clay, flash calciner | K12: Martinez et al. 2023 [117]
A13: [a] Calcined clay, flash calciner | B13: industrial heat, high-temperature | C13: from technosphere (energy_carrier) | D13: energy | E13: 2.7 | F13: GJ | G13: 1 | H13: values found in literature (usually no information given about water content of clay): 2.7 GJ/tonne (Cancio Díaz et al. 2017); 2.8 GJ/tonne (Sánchez Berriel et al. 2016); 3.7 GJ/tonne (Martinez et al. 2023); (not specifying the calcination technology, based on theoretical calculations, but including estimated efficiency loss, Gettu et al. (2018) and Hanein et al. (2021) report values of 2.6 GJ/tonne and 2.2-3 GJ/tonne (for 0 w% water content of clay and assumed thermal process efficiency of 50-70%), respectively) | J13: [a] Calcined clay, flash calciner | K13: Martinez et al. 2023 [117]
A14: [a] Calcined clay, flash calciner | B14: electricity | C14: from technosphere (energy_carrier) | D14: energy | E14: 0.051 | F14: GJ | G14: 1 | H14: none | J14: [a] Calcined clay, flash calciner | K14: Martinez et al. 2023 [117]
A15: [a] Calcined clay, flash calciner | B15: carbon dioxide | C15: to environment (emission, process) | D15: mass | E15: 0.03 | F15: t | G15: 1 | H15: none | I15: Value for electricity demand for "grinding + packing + other" for rotary kiln based industrial scale Metakoalin-Limestone Cement production (Best available technology, flash calciner based production, | J15: [a] Calcined clay, flash calciner | K15: Sánchez Berriel et al. 2016 [116]
A16: [a] Calcined clay, rotary kiln | B16: metakaolin | C16: reference_product | D16: mass | E16: 1 | F16: t | G16: 1 | H16: none | I16: A key determinant of the energy requirements of calcined clay is the moisture content of the used clay. This can highly vary, not only due to the composition of the clay, but also depending on the climatic and weather conditions at the mining site. The moisture content can be as low as a few percent, but can also reach more than 40 wt%. Reducing the free water content/moisture of the clay requires about 600 kJ/kg at 20 wt% of the clay and 1500 kJ/kg at 40 wt%, not considering thermal process efficiency, which varies between 50 and 70 % (Hanein et al. 2021, 20) | J16: [a] Calcined clay, rotary kiln | K16: Hanein et al. 2021 [114] | L16: 2507
A17: [a] Calcined clay, rotary kiln | B17: kaolinite, dry | C17: from environment (natural resource) | D17: mass | E17: 1.16 | F17: t | G17: 1 | H17: none | I17: energy demand (high temperature heat) for dry (0 w% water content) kaolinite input - value taken from Cancio Díaz et al. 2017, which report the lowest value among the studies specifying the calcination technology used; ~900°C used for industrial scale clay calcination in kiln calcination | J17: [a] Calcined clay, rotary kiln | K17: Cancio Díaz et al. 2017 [115]
A18: [a] Calcined clay, rotary kiln | B18: industrial heat, high-temperature | C18: from technosphere (energy_carrier) | D18: energy | E18: 3.1 | F18: GJ | G18: 1 | H18: values found in literature (usually no information given about water content of clay): 3.1 GJ/tonne (Cancio Díaz et al. 2017); 3.2 GJ/tonne (Sánchez Berriel et al. 2016); 4.4 GJ/tonne (Martinez et al. 2023); (not specifying the calcination technology, based on theoretical calculations, but including estimated efficiency loss, Gettu et al. (2018) and Hanein et al. (2021) report values of 2.6 GJ/tonne and 2.2-3 GJ/tonne (for 0 w% water content of clay and assumed thermal process efficiency of 50-70%), respectively) | J18: [a] Calcined clay, rotary kiln | K18: Sánchez Berriel et al. 2016 [116]
A19: [a] Calcined clay, rotary kiln | B19: electricity | C19: from technosphere (energy_carrier) | D19: energy | E19: 0.165 | F19: GJ | G19: 1 | H19: none | I19: “The values of less than 30 g CO2 for clays are based on the assumption that the clay will contain\3 wt% CO2” (Hanein et al. 2021, 21) | J19: [a] Calcined clay, rotary kiln | K19: Hanein et al. 2021 [114]
A20: [a] Calcined clay, rotary kiln | B20: carbon dioxide | C20: to environment (emission, process) | D20: mass | E20: 0.03 | F20: t | G20: 1 | H20: none | J20: [a] Calcined clay, rotary kiln
A21: [a] Copper anode production (Bath smelting and converting) | B21: copper, anode | C21: reference_product | D21: mass | E21: 1 | F21: kg | G21: 1 | H21: none | J21: [PU] Pyro_Bath_Copper | K21: See log sheet | L21: 7402
A22: [a] Copper anode production (Bath smelting and converting) | B22: copper concentrate, sulfide ore | C22: from technosphere (material) | D22: mass | E22: 3.57 | F22: kg | G22: kg | H22: none | J22: [PU] Pyro_Bath_Copper | K22: See log sheet
A23: [a] Copper anode production (Bath smelting and converting) | B23: sulfuric acid | C23: to technosphere (by-product) | D23: mass | E23: 1.52 | F23: kg | G23: kg | H23: none | J23: [PU] Pyro_Bath_Copper | K23: See log sheet | L23: 2807
A24: [a] Copper anode production (Bath smelting and converting) | B24: fuel oil | C24: from technosphere (energy_carrier) | D24: energy | E24: 4.18 | F24: MJ | G24: kg | H24: none | J24: [PU] Pyro_Bath_Copper | K24: See log sheet
A25: [a] Copper anode production (Bath smelting and converting) | B25: electricity | C25: from technosphere (energy_carrier) | D25: energy | E25: 6.9 | F25: MJ | G25: kg | H25: none | J25: [PU] Pyro_Bath_Copper | K25: See log sheet
A26: [a] Copper anode production (Bath smelting and converting) | B26: oxygen | C26: from environment (natural resource) | D26: mass | E26: 2.79 | F26: kg | G26: kg | H26: none | J26: [PU] Pyro_Bath_Copper | K26: See log sheet
A27: [a] Copper anode production (Bath smelting and converting) | B27: industrial oxygen | C27: from technosphere (material) | D27: mass | E27: 1.27 | F27: kg | G27: kg | H27: none | J27: [PU] Pyro_Bath_Copper | K27: See log sheet
A28: [a] Copper anode production (Bath smelting and converting) | B28: silca flux | C28: from technosphere (material) | D28: mass | E28: 0.355 | F28: kg | G28: kg | H28: none | J28: [PU] Pyro_Bath_Copper | K28: See log sheet
A29: [a] Copper anode production (Bath smelting and converting) | B29: limestone | C29: from environment (natural resource) | D29: mass | E29: 0.127 | F29: kg | G29: kg | H29: none | J29: [PU] Pyro_Bath_Copper | K29: See log sheet
A30: [a] Copper anode production (Bath smelting and converting) | B30: scrap | C30: from technosphere (other) | D30: mass | E30: 0.0423 | F30: kg | G30: kg | H30: none | J30: [PU] Pyro_Bath_Copper | K30: See log sheet
A31: [a] Copper anode production (Bath smelting and converting) | B31: water | C31: from environment (natural resource) | D31: mass | E31: 0.355 | F31: kg | G31: kg | H31: none | J31: [PU] Pyro_Bath_Copper | K31: See log sheet
A32: [a] Copper anode production (Bath smelting and converting) | B32: sulfur dioxide | C32: to environment (emission) | D32: mass | E32: 0.45 | F32: kg | G32: kg | H32: none | J32: [PU] Pyro_Bath_Copper | K32: See log sheet | L32: 2807
A33: [a] Copper anode production (Bath smelting and converting) | B33: carbon dioxide | C33: to environment (emission) | D33: mass | E33: 0.39 | F33: kg | G33: kg | H33: none | J33: [PU] Pyro_Bath_Copper | K33: See log sheet | L33: 2520
A34: [a] Copper anode production (Bath smelting and converting) | B34: slag | C34: to technosphere (waste) | D34: mass | E34: 1.91 | F34: kg | G34: kg | H34: none | J34: [PU] Pyro_Bath_Copper | K34: See log sheet
A35: [a] Copper anode production (Continuous smelting and converting) | B35: copper, anode | C35: reference_product | D35: mass | E35: 1 | F35: kg | G35: 1 | H35: none | J35: [PU] Pyro_Cont_Copper | K35: See log sheet | L35: 7402
A36: [a] Copper anode production (Continuous smelting and converting) | B36: copper concentrate, sulfide ore | C36: from technosphere (material) | D36: mass | E36: 3.57 | F36: kg | G36: kg | H36: none | J36: [PU] Pyro_Cont_Copper | K36: See log sheet
A37: [a] Copper anode production (Continuous smelting and converting) | B37: sulfuric acid | C37: to technosphere (by-product) | D37: mass | E37: 2.48 | F37: kg | G37: kg | H37: none | J37: [PU] Pyro_Cont_Copper | K37: See log sheet | L37: 2807
A38: [a] Copper anode production (Continuous smelting and converting) | B38: fuel oil | C38: from technosphere (energy_carrier) | D38: energy | E38: 2.5 | F38: MJ | G38: kg | H38: none | J38: [PU] Pyro_Cont_Copper | K38: See log sheet
A39: [a] Copper anode production (Continuous smelting and converting) | B39: electricity | C39: from technosphere (energy_carrier) | D39: energy | E39: 8.51 | F39: MJ | G39: kg | H39: none | J39: [PU] Pyro_Cont_Copper | K39: See log sheet
A40: [a] Copper anode production (Continuous smelting and converting) | B40: oxygen | C40: from environment (natural resource) | D40: mass | E40: 2.71 | F40: kg | G40: kg | H40: none | J40: [PU] Pyro_Cont_Copper | K40: See log sheet
A41: [a] Copper anode production (Continuous smelting and converting) | B41: silca flux | C41: from technosphere (material) | D41: mass | E41: 0.411 | F41: kg | G41: kg | H41: none | J41: [PU] Pyro_Cont_Copper | K41: See log sheet
A42: [a] Copper anode production (Continuous smelting and converting) | B42: industrial oxygen | C42: from technosphere (material) | D42: mass | E42: 1.47 | F42: kg | G42: kg | H42: none | J42: [PU] Pyro_Cont_Copper | K42: See log sheet
A43: [a] Copper anode production (Continuous smelting and converting) | B43: limestone | C43: from environment (natural resource) | D43: mass | E43: 0.194 | F43: kg | G43: kg | H43: none | J43: [PU] Pyro_Cont_Copper | K43: See log sheet
A44: [a] Copper anode production (Continuous smelting and converting) | B44: scrap | C44: from technosphere (other) | D44: mass | E44: 0.303 | F44: kg | G44: kg | H44: none | J44: [PU] Pyro_Cont_Copper | K44: See log sheet
A45: [a] Copper anode production (Continuous smelting and converting) | B45: water | C45: from environment (natural resource) | D45: mass | E45: 0.545 | F45: kg | G45: kg | H45: none | J45: [PU] Pyro_Cont_Copper | K45: See log sheet
A46: [a] Copper anode production (Continuous smelting and converting) | B46: carbon dioxide | C46: to environment (emission) | D46: mass | E46: 0.285 | F46: kg | G46: kg | H46: none | J46: [PU] Pyro_Cont_Copper | K46: See log sheet
A47: [a] Copper anode production (Continuous smelting and converting) | B47: oleum | C47: to technosphere (by-product) | D47: mass | E47: 0.254 | F47: kg | G47: kg | H47: none | J47: [PU] Pyro_Cont_Copper | K47: See log sheet | L47: 2807
A48: [a] Copper anode production (Continuous smelting and converting) | B48: gypsum | C48: to technosphere (by-product) | D48: mass | E48: 0.303 | F48: kg | G48: kg | H48: none | J48: [PU] Pyro_Cont_Copper | K48: See log sheet | L48: 2520
A49: [a] Copper anode production (Continuous smelting and converting) | B49: slag | C49: to technosphere (waste) | D49: mass | E49: 1.85 | F49: kg | G49: kg | H49: none | J49: [PU] Pyro_Cont_Copper | K49: See log sheet
A50: [a] Copper anode production (Flash smelting and converting) | B50: copper, anode | C50: reference_product | D50: mass | E50: 1 | F50: kg | G50: 1 | H50: none | J50: [PU] Pyro_Flash_Copper | K50: See log sheet | L50: 7402
A51: [a] Copper anode production (Flash smelting and converting) | B51: copper concentrate, sulfide ore | C51: from technosphere (material) | D51: mass | E51: 3.57 | F51: kg | G51: kg | H51: none | J51: [PU] Pyro_Flash_Copper | K51: See log sheet
A52: [a] Copper anode production (Flash smelting and converting) | B52: sulfuric acid | C52: to technosphere (by-product) | D52: mass | E52: 2.2 | F52: kg | G52: kg | H52: none | J52: [PU] Pyro_Flash_Copper | K52: See log sheet | L52: 2807
A53: [a] Copper anode production (Flash smelting and converting) | B53: fuel oil | C53: from technosphere (energy_carrier) | D53: energy | E53: 1.52 | F53: MJ | G53: kg | H53: none | J53: [PU] Pyro_Flash_Copper | K53: See log sheet
A54: [a] Copper anode production (Flash smelting and converting) | B54: electricity | C54: from technosphere (energy_carrier) | D54: energy | E54: 9.27 | F54: MJ | G54: kg | H54: none | J54: [PU] Pyro_Flash_Copper | K54: See log sheet
A55: [a] Copper anode production (Flash smelting and converting) | B55: industrial oxygen | C55: from technosphere (material) | D55: mass | E55: 0.909 | F55: kg | G55: kg | H55: none | J55: [PU] Pyro_Flash_Copper | K55: See log sheet
A56: [a] Copper anode production (Flash smelting and converting) | B56: oxygen | C56: from environment (natural resource) | D56: mass | E56: 1.78 | F56: kg | G56: kg | H56: none | J56: [PU] Pyro_Flash_Copper | K56: See log sheet
A57: [a] Copper anode production (Flash smelting and converting) | B57: silca flux | C57: from technosphere (material) | D57: mass | E57: 0.35 | F57: kg | G57: kg | H57: none | J57: [PU] Pyro_Flash_Copper | K57: See log sheet
A58: [a] Copper anode production (Flash smelting and converting) | B58: limestone | C58: from environment (natural resource) | D58: mass | E58: 0.18 | F58: kg | G58: kg | H58: none | J58: [PU] Pyro_Flash_Copper | K58: See log sheet
A59: [a] Copper anode production (Flash smelting and converting) | B59: scrap | C59: from technosphere (other) | D59: mass | E59: 0.11 | F59: kg | G59: kg | H59: none | J59: [PU] Pyro_Flash_Copper | K59: See log sheet
A60: [a] Copper anode production (Flash smelting and converting) | B60: water | C60: from environment (natural resource) | D60: mass | E60: 0.49 | F60: kg | G60: kg | H60: none | J60: [PU] Pyro_Flash_Copper | K60: See log sheet
A61: [a] Copper anode production (Flash smelting and converting) | B61: sulfur dioxide | C61: to environment (emission) | D61: mass | E61: 0.19 | F61: kg | G61: kg | H61: none | J61: [PU] Pyro_Flash_Copper | K61: See log sheet
A62: [a] Copper anode production (Flash smelting and converting) | B62: carbon dioxide | C62: to environment (emission) | D62: mass | E62: 0.21 | F62: kg | G62: kg | H62: none | J62: [PU] Pyro_Flash_Copper | K62: See log sheet
A63: [a] Copper anode production (Flash smelting and converting) | B63: oleum | C63: to technosphere (by-product) | D63: mass | E63: 0.3 | F63: kg | G63: kg | H63: none | J63: [PU] Pyro_Flash_Copper | K63: See log sheet | L63: 2807
A64: [a] Copper anode production (Flash smelting and converting) | B64: gypsum | C64: to technosphere (by-product) | D64: mass | E64: 0.8 | F64: kg | G64: kg | H64: none | J64: [PU] Pyro_Flash_Copper | K64: See log sheet | L64: 2520
A65: [a] Copper anode production (Flash smelting and converting) | B65: slag | C65: to technosphere (waste) | D65: mass | E65: 1.91 | F65: kg | G65: kg | H65: none | J65: [PU] Pyro_Flash_Copper | K65: See log sheet
A66: [a] Copper anode production, Pyrometallurgy (Hydrogen Reduction) | B66: copper, anode | C66: reference_product | D66: mass | E66: 1 | F66: kg | G66: 1 | H66: none | J66: [PU] Pyro_Copper_Hydrogen | K66: See log sheet | L66: 7402
A67: [a] Copper anode production, Pyrometallurgy (Hydrogen Reduction) | B67: copper concentrate, sulfide ore | C67: from technosphere (material) | D67: mass | E67: 3.57 | F67: kg | G67: kg | H67: none | J67: [PU] Pyro_Copper_Hydrogen | K67: See log sheet
A68: [a] Copper anode production, Pyrometallurgy (Hydrogen Reduction) | B68: sulfuric acid | C68: to technosphere (by-product) | D68: mass | E68: 2.2 | F68: kg | G68: kg | H68: none | J68: [PU] Pyro_Copper_Hydrogen | K68: See log sheet
A69: [a] Copper anode production, Pyrometallurgy (Hydrogen Reduction) | B69: hydrogen | C69: from technosphere (reductant) | D69: mass | E69: 0.0243 | F69: kg | G69: kg | H69: none | J69: [PU] Pyro_Copper_Hydrogen | K69: See log sheet
A70: [a] Copper anode production, Pyrometallurgy (Hydrogen Reduction) | B70: electricity | C70: from technosphere (energy_carrier) | D70: energy | E70: 9.27 | F70: MJ | G70: kg | H70: none | J70: [PU] Pyro_Copper_Hydrogen | K70: See log sheet
A71: [a] Copper anode production, Pyrometallurgy (Hydrogen Reduction) | B71: industrial oxygen | C71: from technosphere (material) | D71: mass | E71: 0.909 | F71: kg | G71: kg | H71: none | J71: [PU] Pyro_Copper_Hydrogen | K71: See log sheet
A72: [a] Copper anode production, Pyrometallurgy (Hydrogen Reduction) | B72: oxygen | C72: from environment (natural resource) | D72: mass | E72: 1.78 | F72: kg | G72: kg | H72: none | J72: [PU] Pyro_Copper_Hydrogen | K72: See log sheet
A73: [a] Copper anode production, Pyrometallurgy (Hydrogen Reduction) | B73: silca flux | C73: from technosphere (material) | D73: mass | E73: 0.35 | F73: kg | G73: kg | H73: none | J73: [PU] Pyro_Copper_Hydrogen | K73: See log sheet
A74: [a] Copper anode production, Pyrometallurgy (Hydrogen Reduction) | B74: scrap | C74: from technosphere (other) | D74: mass | E74: 0.11 | F74: kg | G74: kg | H74: none | J74: [PU] Pyro_Copper_Hydrogen | K74: See log sheet
A75: [a] Copper anode production, Pyrometallurgy (Hydrogen Reduction) | B75: water | C75: from environment (natural resource) | D75: mass | E75: 0.49 | F75: kg | G75: kg | H75: none | J75: [PU] Pyro_Copper_Hydrogen | K75: See log sheet
A76: [a] Copper anode production, Pyrometallurgy (Hydrogen Reduction) | B76: sulfur dioxide | C76: to environment (emission) | D76: mass | E76: 0.19 | F76: kg | G76: kg | H76: none | J76: [PU] Pyro_Copper_Hydrogen | K76: See log sheet
A77: [a] Copper anode production, Pyrometallurgy (Hydrogen Reduction) | B77: water | C77: to technosphere (by-product) | D77: mass | E77: 1.8 | F77: kg | G77: kg | H77: none | J77: [PU] Pyro_Copper_Hydrogen | K77: See log sheet
A78: [a] Copper anode production, Pyrometallurgy (Hydrogen Reduction) | B78: oleum | C78: to technosphere (by-product) | D78: mass | E78: 0.3 | F78: kg | G78: kg | H78: none | J78: [PU] Pyro_Copper_Hydrogen | K78: See log sheet | L78: 2807
A79: [a] Copper anode production, Pyrometallurgy (Hydrogen Reduction) | B79: gypsum | C79: to technosphere (by-product) | D79: mass | E79: 0.8 | F79: kg | G79: kg | H79: none | J79: [PU] Pyro_Copper_Hydrogen | K79: See log sheet | L79: 2520
A80: [a] Copper anode production, Pyrometallurgy (Hydrogen Reduction) | B80: slag | C80: to technosphere (waste) | D80: mass | E80: 1.91 | F80: kg | G80: kg | H80: none | J80: [PU] Pyro_Copper_Hydrogen | K80: See log sheet
A81: [a] Copper cathode production, Hydrometallurgy (leaching, SX, EW) | B81: copper, cathode | C81: reference_product | D81: mass | E81: 1 | F81: kg | G81: 1 | H81: none | J81: [PU] Hydro_Copper | K81: see log sheet | L81: 7403
A82: [a] Copper cathode production, Hydrometallurgy (leaching, SX, EW) | B82: electricity, leaching process | C82: from technosphere (energy_carrier) | D82: energy | E82: 5.22 | F82: MJ | G82: kg | H82: none | J82: [PU] Hydro_Copper | K82: see log sheet
A83: [a] Copper cathode production, Hydrometallurgy (leaching, SX, EW) | B83: water | C83: from environment (natural resource) | D83: volume | E83: 0.0227 | F83: m3 | G83: kg | H83: none | J83: [PU] Hydro_Copper | K83: see log sheet
A84: [a] Copper cathode production, Hydrometallurgy (leaching, SX, EW) | B84: sulfuric acid | C84: from technosphere (material) | D84: mass | E84: 2.95 | F84: kg | G84: kg | H84: none | J84: [PU] Hydro_Copper | K84: see log sheet
A85: [a] Copper cathode production, Hydrometallurgy (leaching, SX, EW) | B85: electricity, SX process | C85: from technosphere (energy_carrier) | D85: energy | E85: 8.46 | F85: MJ | G85: kg | H85: none | J85: [PU] Hydro_Copper | K85: see log sheet
A86: [a] Copper cathode production, Hydrometallurgy (leaching, SX, EW) | B86: electricity, EW process | C86: from technosphere (energy_carrier) | D86: energy | E86: 16.9 | F86: MJ | G86: kg | H86: none | J86: [PU] Hydro_Copper | K86: see log sheet
A87: [a] Copper cathode production, Hydrometallurgy (leaching, SX, EW) | B87: steam | C87: from technosphere (energy_carrier) | D87: mass | E87: 0.000256 | F87: kg | G87: kg | H87: none | J87: [PU] Hydro_Copper | K87: see log sheet
A88: [a] Copper cathode production, Hydrometallurgy (leaching, SX, EW) | B88: oxide ore | C88: from environment (natural resource) | D88: mass | E88: 143 | F88: kg | G88: kg | H88: none | J88: [PU] Hydro_Copper | K88: see log sheet
A89: [a] Copper cathode production, Hydrometallurgy (leaching, SX, EW) | B89: water | C89: to environment (emission) | D89: volume | E89: 0.0227 | F89: m3 | G89: kg | H89: none | J89: [PU] Hydro_Copper | K89: see log sheet
A90: [a] Electrorefining of copper anode | B90: copper, cathode | C90: reference_product | D90: mass | E90: 1 | F90: kg | G90: 1 | H90: none | J90: [PU] Pyro_ElecRef_Copper | K90: See log sheet | L90: 7403
A91: [a] Electrorefining of copper anode | B91: copper, anode | C91: from technosphere (material) | D91: mass | E91: 0.993 | F91: kg | G91: kg | H91: none | J91: [PU] Pyro_ElecRef_Copper | K91: See log sheet
A92: [a] Electrorefining of copper anode | B92: electricity, high voltage | C92: from technosphere (energy_carrier) | D92: energy | E92: 0.4 | F92: kWh | G92: kg | H92: none | J92: [PU] Pyro_ElecRef_Copper | K92: See log sheet
A93: [a] Electrorefining of copper anode | B93: diesel, burned in building machine | C93: from technosphere (energy_carrier) | D93: energy | E93: 2.24 | F93: MJ | G93: kg | H93: none | J93: [PU] Pyro_ElecRef_Copper | K93: See log sheet
A94: [a] Electrorefining of copper anode | B94: electrolyte, copper-rich | C94: from technosphere (material) | D94: mass | E94: 0.00601 | F94: kg | G94: kg | H94: none | J94: [PU] Pyro_ElecRef_Copper | K94: See log sheet
A95: [a] Electrorefining of copper anode | B95: copper-rich materials | C95: from technosphere (material) | D95: mass | E95: 0.00495 | F95: kg | G95: kg | H95: none | J95: [PU] Pyro_ElecRef_Copper | K95: See log sheet
A96: [a] Electrorefining of copper anode | B96: heat, waste | C96: to environment (emission) | D96: energy | E96: 1.77 | F96: MJ | G96: kg | H96: none | J96: [PU] Pyro_ElecRef_Copper | K96: See log sheet
A97: [a] Electrorefining of copper anode | B97: anode slime | C97: to technosphere (by-product) | D97: mass | E97: 0.003 | F97: kg | G97: kg | H97: none | J97: [PU] Pyro_ElecRef_Copper | K97: See log sheet | L97: 711230
A98: [a] naphta production | B98: naphtha | C98: reference_product | D98: mass | E98: 1 | F98: t | G98: 1 | H98: none | J98: Production process inventories for naphta, vinyl chloride, PVC, PP, PE. | L98: 271114
A99: [a] naphta production | B99: natural gas | C99: from technosphere (energy_carrier) | D99: energy | E99: 0.0086 | F99: GJ | G99: 1 | H99: none | J99: Production process inventories for naphta, vinyl chloride, PVC, PP, PE.
A100: [a] naphta production | B100: petroleum | C100: from technosphere (material) | D100: mass | E100: 1.066 | F100: t | G100: 1 | H100: none | J100: Production process inventories for naphta, vinyl chloride, PVC, PP, PE.
...

Sheet Data_old
A1: process | B1: material | C1: material_category | D1: layer | E1: value | F1: unit nominator | G1: unit denominator | H1: stats_array string | I1: comment | J1: link to log entry | K1: Data source | L1: material_group
A2: [a] Beneficiation, sulfide ore (Crushing, grinding, flotation) | B2: copper concentrate, sulfide ore | C2: reference_product | D2: mass | E2: 1 | F2: t | G2: 1 | H2: none | J2: [PU] Sulf_Ore_Conc | K2: See log sheet | L2: 2603
A3: [a] Beneficiation, sulfide ore (Crushing, grinding, flotation) | B3: sulphide ore | C3: from environment (natural resource) | D3: mass | E3: 4 | F3: t | G3: t | H3: none | J3: [PU] Sulf_Ore_Conc | K3: See log sheet
A4: [a] Beneficiation, sulfide ore (Crushing, grinding, flotation) | B4: electricity | C4: from technosphere (energy_carrier) | D4: energy | E4: 16.4 | F4: kWh | G4: t | H4: none | J4: [PU] Sulf_Ore_Conc | K4: See log sheet
A5: [a] Beneficiation, sulfide ore (Crushing, grinding, flotation) | B5: water | C5: from environment (natural resource) | D5: volume | E5: 0.6 | F5: m3 | G5: t | H5: none | J5: [PU] Sulf_Ore_Conc | K5: See log sheet
A6: [a] Beneficiation, sulfide ore (Crushing, grinding, flotation) | B6: steel | C6: from technosphere (material) | D6: mass | E6: 0.7 | F6: t | G6: t | H6: none | J6: [PU] Sulf_Ore_Conc | K6: See log sheet
A7: [a] Beneficiation, sulfide ore (Crushing, grinding, flotation) | B7: quicklime | C7: from technosphere (material) | D7: mass | E7: 1 | F7: t | G7: t | H7: none | J7: [PU] Sulf_Ore_Conc | K7: See log sheet
A8: [a] Beneficiation, sulfide ore (Crushing, grinding, flotation) | B8: other chemicals | C8: from technosphere (material) | D8: mass | E8: 0.13 | F8: t | G8: t | H8: none | J8: [PU] Sulf_Ore_Conc | K8: See log sheet
A9: [a] Beneficiation, sulfide ore (Crushing, grinding, flotation) | B9: water | C9: to environment (emission) | D9: volume | E9: 0.6 | F9: m3 | G9: t | H9: none | J9: [PU] Sulf_Ore_Conc | K9: See log sheet
A10: [a] Beneficiation, sulfide ore (Crushing, grinding, flotation) | B10: tailings | C10: to technosphere (waste) | D10: mass | E10: 5.83 | F10: t | G10: t | H10: none | J10: [PU] Sulf_Ore_Conc | K10: See log sheet
A11: [a] Calcined clay, flash calciner | B11: metakaolin | C11: reference_product | D11: mass | E11: 1 | F11: t | G11: 1 | H11: none | J11: [a] Calcined clay, flash calciner | K11: Martinez et al. 2023 [117] | L11: 2507
A12: [a] Calcined clay, flash calciner | B12: kaolinite, dry | C12: from environment (natural resource) | D12: mass | E12: 1.16 | F12: t | G12: 1 | H12: none | J12: [a] Calcined clay, flash calciner | K12: Martinez et al. 2023 [117]
A13: [a] Calcined clay, flash calciner | B13: industrial heat, high-temperature | C13: from technosphere (energy_carrier) | D13: energy | E13: 2.7 | F13: GJ | G13: 1 | H13: values found in literature (usually no information given about water content of clay): 2.7 GJ/tonne (Cancio Díaz et al. 2017); 2.8 GJ/tonne (Sánchez Berriel et al. 2016); 3.7 GJ/tonne (Martinez et al. 2023); (not specifying the calcination technology, based on theoretical calculations, but including estimated efficiency loss, Gettu et al. (2018) and Hanein et al. (2021) report values of 2.6 GJ/tonne and 2.2-3 GJ/tonne (for 0 w% water content of clay and assumed thermal process efficiency of 50-70%), respectively) | J13: [a] Calcined clay, flash calciner | K13: Martinez et al. 2023 [117]
A14: [a] Calcined clay, flash calciner | B14: electricity | C14: from technosphere (energy_carrier) | D14: energy | E14: 0.051 | F14: GJ | G14: 1 | H14: none | J14: [a] Calcined clay, flash calciner | K14: Martinez et al. 2023 [117]
A15: [a] Calcined clay, flash calciner | B15: carbon dioxide | C15: to environment (emission, process) | D15: mass | E15: 0.03 | F15: t | G15: 1 | H15: none | I15: Value for electricity demand for "grinding + packing + other" for rotary kiln based industrial scale Metakoalin-Limestone Cement production (Best available technology, flash calciner based production, | J15: [a] Calcined clay, flash calciner | K15: Sánchez Berriel et al. 2016 [116]
A16: [a] Calcined clay, rotary kiln | B16: metakaolin | C16: reference_product | D16: mass | E16: 1 | F16: t | G16: 1 | H16: none | I16: A key determinant of the energy requirements of calcined clay is the moisture content of the used clay. This can highly vary, not only due to the composition of the clay, but also depending on the climatic and weather conditions at the mining site. The moisture content can be as low as a few percent, but can also reach more than 40 wt%. Reducing the free water content/moisture of the clay requires about 600 kJ/kg at 20 wt% of the clay and 1500 kJ/kg at 40 wt%, not considering thermal process efficiency, which varies between 50 and 70 % (Hanein et al. 2021, 20) | J16: [a] Calcined clay, rotary kiln | K16: Hanein et al. 2021 [114] | L16: 2507
A17: [a] Calcined clay, rotary kiln | B17: kaolinite, dry | C17: from environment (natural resource) | D17: mass | E17: 1.16 | F17: t | G17: 1 | H17: none | I17: energy demand (high temperature heat) for dry (0 w% water content) kaolinite input - value taken from Cancio Díaz et al. 2017, which report the lowest value among the studies specifying the calcination technology used; ~900°C used for industrial scale clay calcination in kiln calcination | J17: [a] Calcined clay, rotary kiln | K17: Cancio Díaz et al. 2017 [115]
A18: [a] Calcined clay, rotary kiln | B18: industrial heat, high-temperature | C18: from technosphere (energy_carrier) | D18: energy | E18: 3.1 | F18: GJ | G18: 1 | H18: values found in literature (usually no information given about water content of clay): 3.1 GJ/tonne (Cancio Díaz et al. 2017); 3.2 GJ/tonne (Sánchez Berriel et al. 2016); 4.4 GJ/tonne (Martinez et al. 2023); (not specifying the calcination technology, based on theoretical calculations, but including estimated efficiency loss, Gettu et al. (2018) and Hanein et al. (2021) report values of 2.6 GJ/tonne and 2.2-3 GJ/tonne (for 0 w% water content of clay and assumed thermal process efficiency of 50-70%), respectively) | J18: [a] Calcined clay, rotary kiln | K18: Sánchez Berriel et al. 2016 [116]
A19: [a] Calcined clay, rotary kiln | B19: electricity | C19: from technosphere (energy_carrier) | D19: energy | E19: 0.165 | F19: GJ | G19: 1 | H19: none | I19: “The values of less than 30 g CO2 for clays are based on the assumption that the clay will contain\3 wt% CO2” (Hanein et al. 2021, 21) | J19: [a] Calcined clay, rotary kiln | K19: Hanein et al. 2021 [114]
A20: [a] Calcined clay, rotary kiln | B20: carbon dioxide | C20: to environment (emission, process) | D20: mass | E20: 0.03 | F20: t | G20: 1 | H20: none | J20: [a] Calcined clay, rotary kiln
A21: [a] Copper anode production (Bath smelting and converting) | B21: copper, anode | C21: reference_product | D21: mass | E21: 1 | F21: kg | G21: 1 | H21: none | J21: [PU] Pyro_Bath_Copper | K21: See log sheet | L21: 7402
A22: [a] Copper anode production (Bath smelting and converting) | B22: copper concentrate, sulfide ore | C22: from technosphere (material) | D22: mass | E22: 3.57 | F22: kg | G22: kg | H22: none | J22: [PU] Pyro_Bath_Copper | K22: See log sheet
A23: [a] Copper anode production (Bath smelting and converting) | B23: sulfuric acid | C23: to technosphere (by-product) | D23: mass | E23: 1.52 | F23: kg | G23: kg | H23: none | J23: [PU] Pyro_Bath_Copper | K23: See log sheet | L23: 2807
A24: [a] Copper anode production (Bath smelting and converting) | B24: fuel oil | C24: from technosphere (energy_carrier) | D24: energy | E24: 4.18 | F24: MJ | G24: kg | H24: none | J24: [PU] Pyro_Bath_Copper | K24: See log sheet
A25: [a] Copper anode production (Bath smelting and converting) | B25: electricity | C25: from technosphere (energy_carrier) | D25: energy | E25: 6.9 | F25: MJ | G25: kg | H25: none | J25: [PU] Pyro_Bath_Copper | K25: See log sheet
A26: [a] Copper anode production (Bath smelting and converting) | B26: oxygen | C26: from environment (natural resource) | D26: mass | E26: 2.79 | F26: kg | G26: kg | H26: none | J26: [PU] Pyro_Bath_Copper | K26: See log sheet
A27: [a] Copper anode production (Bath smelting and converting) | B27: industrial oxygen | C27: from technosphere (material) | D27: mass | E27: 1.27 | F27: kg | G27: kg | H27: none | J27: [PU] Pyro_Bath_Copper | K27: See log sheet
A28: [a] Copper anode production (Bath smelting and converting) | B28: silca flux | C28: from technosphere (material) | D28: mass | E28: 0.355 | F28: kg | G28: kg | H28: none | J28: [PU] Pyro_Bath_Copper | K28: See log sheet
A29: [a] Copper anode production (Bath smelting and converting) | B29: limestone | C29: from environment (natural resource) | D29: mass | E29: 0.127 | F29: kg | G29: kg | H29: none | J29: [PU] Pyro_Bath_Copper | K29: See log sheet
A30: [a] Copper anode production (Bath smelting and converting) | B30: scrap | C30: from technosphere (other) | D30: mass | E30: 0.0423 | F30: kg | G30: kg | H30: none | J30: [PU] Pyro_Bath_Copper | K30: See log sheet
A31: [a] Copper anode production (Bath smelting and converting) | B31: water | C31: from environment (natural resource) | D31: mass | E31: 0.355 | F31: kg | G31: kg | H31: none | J31: [PU] Pyro_Bath_Copper | K31: See log sheet
A32: [a] Copper anode production (Bath smelting and converting) | B32: sulfur dioxide | C32: to environment (emission) | D32: mass | E32: 0.45 | F32: kg | G32: kg | H32: none | J32: [PU] Pyro_Bath_Copper | K32: See log sheet | L32: 2807
A33: [a] Copper anode production (Bath smelting and converting) | B33: carbon dioxide | C33: to environment (emission) | D33: mass | E33: 0.39 | F33: kg | G33: kg | H33: none | J33: [PU] Pyro_Bath_Copper | K33: See log sheet | L33: 2520
A34: [a] Copper anode production (Bath smelting and converting) | B34: slag | C34: to technosphere (waste) | D34: mass | E34: 1.91 | F34: kg | G34: kg | H34: none | J34: [PU] Pyro_Bath_Copper | K34: See log sheet
A35: [a] Copper anode production (Continuous smelting and converting) | B35: copper, anode | C35: reference_product | D35: mass | E35: 1 | F35: kg | G35: 1 | H35: none | J35: [PU] Pyro_Cont_Copper | K35: See log sheet | L35: 7402
A36: [a] Copper anode production (Continuous smelting and converting) | B36: copper concentrate, sulfide ore | C36: from technosphere (material) | D36: mass | E36: 3.57 | F36: kg | G36: kg | H36: none | J36: [PU] Pyro_Cont_Copper | K36: See log sheet
A37: [a] Copper anode production (Continuous smelting and converting) | B37: sulfuric acid | C37: to technosphere (by-product) | D37: mass | E37: 2.48 | F37: kg | G37: kg | H37: none | J37: [PU] Pyro_Cont_Copper | K37: See log sheet | L37: 2807
A38: [a] Copper anode production (Continuous smelting and converting) | B38: fuel oil | C38: from technosphere (energy_carrier) | D38: energy | E38: 2.5 | F38: MJ | G38: kg | H38: none | J38: [PU] Pyro_Cont_Copper | K38: See log sheet
A39: [a] Copper anode production (Continuous smelting and converting) | B39: electricity | C39: from technosphere (energy_carrier) | D39: energy | E39: 8.51 | F39: MJ | G39: kg | H39: none | J39: [PU] Pyro_Cont_Copper | K39: See log sheet
A40: [a] Copper anode production (Continuous smelting and converting) | B40: oxygen | C40: from environment (natural resource) | D40: mass | E40: 2.71 | F40: kg | G40: kg | H40: none | J40: [PU] Pyro_Cont_Copper | K40: See log sheet
A41: [a] Copper anode production (Continuous smelting and converting) | B41: silca flux | C41: from technosphere (material) | D41: mass | E41: 0.411 | F41: kg | G41: kg | H41: none | J41: [PU] Pyro_Cont_Copper | K41: See log sheet
A42: [a] Copper anode production (Continuous smelting and converting) | B42: industrial oxygen | C42: from technosphere (material) | D42: mass | E42: 1.47 | F42: kg | G42: kg | H42: none | J42: [PU] Pyro_Cont_Copper | K42: See log sheet
A43: [a] Copper anode production (Continuous smelting and converting) | B43: limestone | C43: from environment (natural resource) | D43: mass | E43: 0.194 | F43: kg | G43: kg | H43: none | J43: [PU] Pyro_Cont_Copper | K43: See log sheet
A44: [a] Copper anode production (Continuous smelting and converting) | B44: scrap | C44: from technosphere (other) | D44: mass | E44: 0.303 | F44: kg | G44: kg | H44: none | J44: [PU] Pyro_Cont_Copper | K44: See log sheet
A45: [a] Copper anode production (Continuous smelting and converting) | B45: water | C45: from environment (natural resource) | D45: mass | E45: 0.545 | F45: kg | G45: kg | H45: none | J45: [PU] Pyro_Cont_Copper | K45: See log sheet
A46: [a] Copper anode production (Continuous smelting and converting) | B46: carbon dioxide | C46: to environment (emission) | D46: mass | E46: 0.285 | F46: kg | G46: kg | H46: none | J46: [PU] Pyro_Cont_Copper | K46: See log sheet
A47: [a] Copper anode production (Continuous smelting and converting) | B47: oleum | C47: to technosphere (by-product) | D47: mass | E47: 0.254 | F47: kg | G47: kg | H47: none | J47: [PU] Pyro_Cont_Copper | K47: See log sheet | L47: 2807
A48: [a] Copper anode production (Continuous smelting and converting) | B48: gypsum | C48: to technosphere (by-product) | D48: mass | E48: 0.303 | F48: kg | G48: kg | H48: none | J48: [PU] Pyro_Cont_Copper | K48: See log sheet | L48: 2520
A49: [a] Copper anode production (Continuous smelting and converting) | B49: slag | C49: to technosphere (waste) | D49: mass | E49: 1.85 | F49: kg | G49: kg | H49: none | J49: [PU] Pyro_Cont_Copper | K49: See log sheet
A50: [a] Copper anode production (Flash smelting and converting) | B50: copper, anode | C50: reference_product | D50: mass | E50: 1 | F50: kg | G50: 1 | H50: none | J50: [PU] Pyro_Flash_Copper | K50: See log sheet | L50: 7402
A51: [a] Copper anode production (Flash smelting and converting) | B51: copper concentrate, sulfide ore | C51: from technosphere (material) | D51: mass | E51: 3.57 | F51: kg | G51: kg | H51: none | J51: [PU] Pyro_Flash_Copper | K51: See log sheet
A52: [a] Copper anode production (Flash smelting and converting) | B52: sulfuric acid | C52: to technosphere (by-product) | D52: mass | E52: 2.2 | F52: kg | G52: kg | H52: none | J52: [PU] Pyro_Flash_Copper | K52: See log sheet | L52: 2807
A53: [a] Copper anode production (Flash smelting and converting) | B53: fuel oil | C53: from technosphere (energy_carrier) | D53: energy | E53: 1.52 | F53: MJ | G53: kg | H53: none | J53: [PU] Pyro_Flash_Copper | K53: See log sheet
A54: [a] Copper anode production (Flash smelting and converting) | B54: electricity | C54: from technosphere (energy_carrier) | D54: energy | E54: 9.27 | F54: MJ | G54: kg | H54: none | J54: [PU] Pyro_Flash_Copper | K54: See log sheet
A55: [a] Copper anode production (Flash smelting and converting) | B55: industrial oxygen | C55: from technosphere (material) | D55: mass | E55: 0.909 | F55: kg | G55: kg | H55: none | J55: [PU] Pyro_Flash_Copper | K55: See log sheet
A56: [a] Copper anode production (Flash smelting and converting) | B56: oxygen | C56: from environment (natural resource) | D56: mass | E56: 1.78 | F56: kg | G56: kg | H56: none | J56: [PU] Pyro_Flash_Copper | K56: See log sheet
A57: [a] Copper anode production (Flash smelting and converting) | B57: silca flux | C57: from technosphere (material) | D57: mass | E57: 0.35 | F57: kg | G57: kg | H57: none | J57: [PU] Pyro_Flash_Copper | K57: See log sheet
A58: [a] Copper anode production (Flash smelting and converting) | B58: limestone | C58: from environment (natural resource) | D58: mass | E58: 0.18 | F58: kg | G58: kg | H58: none | J58: [PU] Pyro_Flash_Copper | K58: See log sheet
A59: [a] Copper anode production (Flash smelting and converting) | B59: scrap | C59: from technosphere (other) | D59: mass | E59: 0.11 | F59: kg | G59: kg | H59: none | J59: [PU] Pyro_Flash_Copper | K59: See log sheet
A60: [a] Copper anode production (Flash smelting and converting) | B60: water | C60: from environment (natural resource) | D60: mass | E60: 0.49 | F60: kg | G60: kg | H60: none | J60: [PU] Pyro_Flash_Copper | K60: See log sheet
A61: [a] Copper anode production (Flash smelting and converting) | B61: sulfur dioxide | C61: to environment (emission) | D61: mass | E61: 0.19 | F61: kg | G61: kg | H61: none | J61: [PU] Pyro_Flash_Copper | K61: See log sheet
A62: [a] Copper anode production (Flash smelting and converting) | B62: carbon dioxide | C62: to environment (emission) | D62: mass | E62: 0.21 | F62: kg | G62: kg | H62: none | J62: [PU] Pyro_Flash_Copper | K62: See log sheet
A63: [a] Copper anode production (Flash smelting and converting) | B63: oleum | C63: to technosphere (by-product) | D63: mass | E63: 0.3 | F63: kg | G63: kg | H63: none | J63: [PU] Pyro_Flash_Copper | K63: See log sheet | L63: 2807
A64: [a] Copper anode production (Flash smelting and converting) | B64: gypsum | C64: to technosphere (by-product) | D64: mass | E64: 0.8 | F64: kg | G64: kg | H64: none | J64: [PU] Pyro_Flash_Copper | K64: See log sheet | L64: 2520
A65: [a] Copper anode production (Flash smelting and converting) | B65: slag | C65: to technosphere (waste) | D65: mass | E65: 1.91 | F65: kg | G65: kg | H65: none | J65: [PU] Pyro_Flash_Copper | K65: See log sheet
A66: [a] Copper anode production, Pyrometallurgy (Hydrogen Reduction) | B66: copper, anode | C66: reference_product | D66: mass | E66: 1 | F66: kg | G66: 1 | H66: none | J66: [PU] Pyro_Copper_Hydrogen | K66: See log sheet | L66: 7402
A67: [a] Copper anode production, Pyrometallurgy (Hydrogen Reduction) | B67: copper concentrate, sulfide ore | C67: from technosphere (material) | D67: mass | E67: 3.57 | F67: kg | G67: kg | H67: none | J67: [PU] Pyro_Copper_Hydrogen | K67: See log sheet
A68: [a] Copper anode production, Pyrometallurgy (Hydrogen Reduction) | B68: sulfuric acid | C68: to technosphere (by-product) | D68: mass | E68: 2.2 | F68: kg | G68: kg | H68: none | J68: [PU] Pyro_Copper_Hydrogen | K68: See log sheet
A69: [a] Copper anode production, Pyrometallurgy (Hydrogen Reduction) | B69: hydrogen | C69: from technosphere (reductant) | D69: mass | E69: 0.0243 | F69: kg | G69: kg | H69: none | J69: [PU] Pyro_Copper_Hydrogen | K69: See log sheet
A70: [a] Copper anode production, Pyrometallurgy (Hydrogen Reduction) | B70: electricity | C70: from technosphere (energy_carrier) | D70: energy | E70: 9.27 | F70: MJ | G70: kg | H70: none | J70: [PU] Pyro_Copper_Hydrogen | K70: See log sheet
A71: [a] Copper anode production, Pyrometallurgy (Hydrogen Reduction) | B71: industrial oxygen | C71: from technosphere (material) | D71: mass | E71: 0.909 | F71: kg | G71: kg | H71: none | J71: [PU] Pyro_Copper_Hydrogen | K71: See log sheet
A72: [a] Copper anode production, Pyrometallurgy (Hydrogen Reduction) | B72: oxygen | C72: from environment (natural resource) | D72: mass | E72: 1.78 | F72: kg | G72: kg | H72: none | J72: [PU] Pyro_Copper_Hydrogen | K72: See log sheet
A73: [a] Copper anode production, Pyrometallurgy (Hydrogen Reduction) | B73: silca flux | C73: from technosphere (material) | D73: mass | E73: 0.35 | F73: kg | G73: kg | H73: none | J73: [PU] Pyro_Copper_Hydrogen | K73: See log sheet
A74: [a] Copper anode production, Pyrometallurgy (Hydrogen Reduction) | B74: scrap | C74: from technosphere (other) | D74: mass | E74: 0.11 | F74: kg | G74: kg | H74: none | J74: [PU] Pyro_Copper_Hydrogen | K74: See log sheet
A75: [a] Copper anode production, Pyrometallurgy (Hydrogen Reduction) | B75: water | C75: from environment (natural resource) | D75: mass | E75: 0.49 | F75: kg | G75: kg | H75: none | J75: [PU] Pyro_Copper_Hydrogen | K75: See log sheet
A76: [a] Copper anode production, Pyrometallurgy (Hydrogen Reduction) | B76: sulfur dioxide | C76: to environment (emission) | D76: mass | E76: 0.19 | F76: kg | G76: kg | H76: none | J76: [PU] Pyro_Copper_Hydrogen | K76: See log sheet
A77: [a] Copper anode production, Pyrometallurgy (Hydrogen Reduction) | B77: water | C77: to technosphere (by-product) | D77: mass | E77: 1.8 | F77: kg | G77: kg | H77: none | J77: [PU] Pyro_Copper_Hydrogen | K77: See log sheet
A78: [a] Copper anode production, Pyrometallurgy (Hydrogen Reduction) | B78: oleum | C78: to technosphere (by-product) | D78: mass | E78: 0.3 | F78: kg | G78: kg | H78: none | J78: [PU] Pyro_Copper_Hydrogen | K78: See log sheet | L78: 2807
A79: [a] Copper anode production, Pyrometallurgy (Hydrogen Reduction) | B79: gypsum | C79: to technosphere (by-product) | D79: mass | E79: 0.8 | F79: kg | G79: kg | H79: none | J79: [PU] Pyro_Copper_Hydrogen | K79: See log sheet | L79: 2520
A80: [a] Copper anode production, Pyrometallurgy (Hydrogen Reduction) | B80: slag | C80: to technosphere (waste) | D80: mass | E80: 1.91 | F80: kg | G80: kg | H80: none | J80: [PU] Pyro_Copper_Hydrogen | K80: See log sheet
A81: [a] Copper cathode production, Hydrometallurgy (leaching, SX, EW) | B81: copper, cathode | C81: reference_product | D81: mass | E81: 1 | F81: kg | G81: 1 | H81: none | J81: [PU] Hydro_Copper | K81: see log sheet | L81: 7403
A82: [a] Copper cathode production, Hydrometallurgy (leaching, SX, EW) | B82: electricity, leaching process | C82: from technosphere (energy_carrier) | D82: energy | E82: 5.22 | F82: MJ | G82: kg | H82: none | J82: [PU] Hydro_Copper | K82: see log sheet
A83: [a] Copper cathode production, Hydrometallurgy (leaching, SX, EW) | B83: water | C83: from environment (natural resource) | D83: volume | E83: 0.0227 | F83: m3 | G83: kg | H83: none | J83: [PU] Hydro_Copper | K83: see log sheet
A84: [a] Copper cathode production, Hydrometallurgy (leaching, SX, EW) | B84: sulfuric acid | C84: from technosphere (material) | D84: mass | E84: 2.95 | F84: kg | G84: kg | H84: none | J84: [PU] Hydro_Copper | K84: see log sheet
A85: [a] Copper cathode production, Hydrometallurgy (leaching, SX, EW) | B85: electricity, SX process | C85: from technosphere (energy_carrier) | D85: energy | E85: 8.46 | F85: MJ | G85: kg | H85: none | J85: [PU] Hydro_Copper | K85: see log sheet
A86: [a] Copper cathode production, Hydrometallurgy (leaching, SX, EW) | B86: electricity, EW process | C86: from technosphere (energy_carrier) | D86: energy | E86: 16.9 | F86: MJ | G86: kg | H86: none | J86: [PU] Hydro_Copper | K86: see log sheet
A87: [a] Copper cathode production, Hydrometallurgy (leaching, SX, EW) | B87: steam | C87: from technosphere (energy_carrier) | D87: mass | E87: 0.000256 | F87: kg | G87: kg | H87: none | J87: [PU] Hydro_Copper | K87: see log sheet
A88: [a] Copper cathode production, Hydrometallurgy (leaching, SX, EW) | B88: oxide ore | C88: from environment (natural resource) | D88: mass | E88: 143 | F88: kg | G88: kg | H88: none | J88: [PU] Hydro_Copper | K88: see log sheet
A89: [a] Copper cathode production, Hydrometallurgy (leaching, SX, EW) | B89: water | C89: to environment (emission) | D89: volume | E89: 0.0227 | F89: m3 | G89: kg | H89: none | J89: [PU] Hydro_Copper | K89: see log sheet
A90: [a] Electrorefining of copper anode | B90: copper, cathode | C90: reference_product | D90: mass | E90: 1 | F90: kg | G90: 1 | H90: none | J90: [PU] Pyro_ElecRef_Copper | K90: See log sheet | L90: 7403
A91: [a] Electrorefining of copper anode | B91: copper, anode | C91: from technosphere (material) | D91: mass | E91: 0.993 | F91: kg | G91: kg | H91: none | J91: [PU] Pyro_ElecRef_Copper | K91: See log sheet
A92: [a] Electrorefining of copper anode | B92: electricity, high voltage | C92: from technosphere (energy_carrier) | D92: energy | E92: 0.4 | F92: kWh | G92: kg | H92: none | J92: [PU] Pyro_ElecRef_Copper | K92: See log sheet
A93: [a] Electrorefining of copper anode | B93: diesel, burned in building machine | C93: from technosphere (energy_carrier) | D93: energy | E93: 2.24 | F93: MJ | G93: kg | H93: none | J93: [PU] Pyro_ElecRef_Copper | K93: See log sheet
A94: [a] Electrorefining of copper anode | B94: electrolyte, copper-rich | C94: from technosphere (material) | D94: mass | E94: 0.00601 | F94: kg | G94: kg | H94: none | J94: [PU] Pyro_ElecRef_Copper | K94: See log sheet
A95: [a] Electrorefining of copper anode | B95: copper-rich materials | C95: from technosphere (material) | D95: mass | E95: 0.00495 | F95: kg | G95: kg | H95: none | J95: [PU] Pyro_ElecRef_Copper | K95: See log sheet
A96: [a] Electrorefining of copper anode | B96: heat, waste | C96: to environment (emission) | D96: energy | E96: 1.77 | F96: MJ | G96: kg | H96: none | J96: [PU] Pyro_ElecRef_Copper | K96: See log sheet
A97: [a] Electrorefining of copper anode | B97: anode slime | C97: to technosphere (by-product) | D97: mass | E97: 0.003 | F97: kg | G97: kg | H97: none | J97: [PU] Pyro_ElecRef_Copper | K97: See log sheet | L97: 711230
A98: [a] naphta production | B98: naphtha | C98: reference_product | D98: mass | E98: 1 | F98: t | G98: 1 | H98: none | J98: Production process inventories for naphta, vinyl chloride, PVC, PP, PE. | L98: 271114
A99: [a] naphta production | B99: natural gas | C99: from technosphere (energy_carrier) | D99: energy | E99: 0.0086 | F99: GJ | G99: 1 | H99: none | J99: Production process inventories for naphta, vinyl chloride, PVC, PP, PE.
A100: [a] naphta production | B100: petroleum | C100: from technosphere (material) | D100: mass | E100: 1.066 | F100: t | G100: 1 | H100: none | J100: Production process inventories for naphta, vinyl chloride, PVC, PP, PE.
...

Sheet log
A2: Log entry name (link to column I on Data sheet) | B2: Which process? (check CM_1: material_processing_technologies for existing labels) | C2: Which NACE_rev2 code? Does the process cover the entire NACE (revision 2) code category or only part of it? See iedc classification 57 or https://github.com/IndEcol/SEM_classifications/blob/master/processes/IEDC_57_NACE_REV2.xlsx for a complete list) | D2: Date | E2: Who | F2: What - detailed description | G2: List items of ref sheet used
A3: [IMAGE] DRY | B3: Standard dry feed rotary kiln | C3: Part of 23.51 (Manufacture of cement) | D3: 45092 | E3: zotin | F3: Input data used in the IMAGE model, see also van Ruijven et al. (2016) and van Sluisveld et al. (2021). | G3: 2,3,4,5
F4: Additional comments, assumptions, and proxy choices made: | L4: {=IFERROR(VLOOKUP(A10,Data_old!$A:$J,Data_old!$A:$A,FALSE),"")}
F5: Tbd. | L5: {=IFERROR(VLOOKUP(A11,Data_old!$A:$J,Data_old!$A:$A,FALSE),"")}
F6: Qualitative evaluation of the data | L6: {=IFERROR(VLOOKUP(A12,Data_old!$A:$J,Data_old!$A:$A,FALSE),"")}
F7: Tbd. | L7: {=IFERROR(VLOOKUP(A13,Data_old!$A:$J,Data_old!$A:$A,FALSE),"")}
L8: {=IFERROR(VLOOKUP(A14,Data_old!$A:$J,Data_old!$A:$A,FALSE),"")}
A9: [IMAGE] EFD | B9: Efficient dry feed rotary kiln | C9: Part of 23.51 (Manufacture of cement) | D9: 45092 | E9: zotin | F9: Input data used in the IMAGE model, see also van Ruijven et al. (2016) and van Sluisveld et al. (2021). | G9: 2,3,4,5 | L9: {=IFERROR(VLOOKUP(A15,Data_old!$A:$J,Data_old!$A:$A,FALSE),"")}
F10: Additional comments, assumptions, and proxy choices made: | L10: {=IFERROR(VLOOKUP(A16,Data_old!$A:$J,Data_old!$A:$A,FALSE),"")}
F11: Tbd. | L11: {=IFERROR(VLOOKUP(A17,Data_old!$A:$J,Data_old!$A:$A,FALSE),"")}
F12: Qualitative evaluation of the data | L12: {=IFERROR(VLOOKUP(A18,Data_old!$A:$J,Data_old!$A:$A,FALSE),"")}
F13: Tbd. | L13: {=IFERROR(VLOOKUP(A19,Data_old!$A:$J,Data_old!$A:$A,FALSE),"")}
L14: {=IFERROR(VLOOKUP(A20,Data_old!$A:$J,Data_old!$A:$A,FALSE),"")}
A15: [IMAGE] EFD+CCS1 | B15: Efficient dry feed rotary kiln + on-site CCS | C15: Part of 23.51 (Manufacture of cement) | D15: 45092 | E15: zotin | F15: Input data used in the IMAGE model, see also van Ruijven et al. (2016) and van Sluisveld et al. (2021). | G15: 2,3,4,5 | L15: {=IFERROR(VLOOKUP(A21,Data_old!$A:$J,Data_old!$A:$A,FALSE),"")}
F16: Additional comments, assumptions, and proxy choices made: | L16: {=IFERROR(VLOOKUP(A22,Data_old!$A:$J,Data_old!$A:$A,FALSE),"")}
F17: Tbd. | L17: {=IFERROR(VLOOKUP(A23,Data_old!$A:$J,Data_old!$A:$A,FALSE),"")}
F18: Qualitative evaluation of the data | L18: {=IFERROR(VLOOKUP(A24,Data_old!$A:$J,Data_old!$A:$A,FALSE),"")}
F19: Tbd. | L19: {=IFERROR(VLOOKUP(A25,Data_old!$A:$J,Data_old!$A:$A,FALSE),"")}
L20: {=IFERROR(VLOOKUP(A26,Data_old!$A:$J,Data_old!$A:$A,FALSE),"")}
A21: [IMAGE] EFD+CCS2 | B21: Efficient dry feed rotary kiln + oxy-combustion CCS | C21: Part of 23.51 (Manufacture of cement) | D21: 45092 | E21: zotin | F21: Input data used in the IMAGE model, see also van Ruijven et al. (2016) and van Sluisveld et al. (2021). | G21: 2,3,4,5
F22: Additional comments, assumptions, and proxy choices made:
F23: Tbd.
F24: Qualitative evaluation of the data
F25: Tbd.
A27: [IMAGE] BF/BOF | B27: Blast Furnace + Basic Oxygen Furnace | C27: Part of 24.1 (Manufacture of basic iron and steel and of ferro-alloys) | D27: 45092 | E27: zotin | F27: Input data used in the IMAGE model, see also van Ruijven et al. (2016) and van Sluisveld et al. (2021). | G27: 2,3,4,5
F28: Additional comments, assumptions, and proxy choices made:
F29: Tbd.
F30: Qualitative evaluation of the data
F31: Tbd.
A33: [IMAGE] DRI/EAF | B33: Direct Reduced Iron + Electric Arc Furnace | C33: Part of 24.1 (Manufacture of basic iron and steel and of ferro-alloys) | D33: 45092 | E33: zotin | F33: Input data used in the IMAGE model, see also van Ruijven et al. (2016) and van Sluisveld et al. (2021). | G33: 2,3,4,5
F34: Additional comments, assumptions, and proxy choices made:
F35: Tbd.
F36: Qualitative evaluation of the data
F37: Tbd.
A39: [IMAGE] EAF-scrap | B39: Standard Electric Arc Furnace - Scrap | C39: Part of 24.1 (Manufacture of basic iron and steel and of ferro-alloys) | D39: 45092 | E39: zotin | F39: Input data used in the IMAGE model, see also van Ruijven et al. (2016) and van Sluisveld et al. (2021). | G39: 2,3,4,5
F40: Additional comments, assumptions, and proxy choices made:
F41: Tbd.
F42: Qualitative evaluation of the data
F43: Tbd.
A45: [IMAGE] Eff. BF/BOF | B45: Modernized Blast Furnace + Basic Oxygen Furnace | C45: Part of 24.1 (Manufacture of basic iron and steel and of ferro-alloys) | D45: 45092 | E45: zotin | F45: Input data used in the IMAGE model, see also van Ruijven et al. (2016) and van Sluisveld et al. (2021). | G45: 2,3,4,5
F46: Additional comments, assumptions, and proxy choices made:
F47: Tbd.
F48: Qualitative evaluation of the data
F49: Tbd.
A51: [IMAGE] BF/BOF+CCS | B51: Blast Furnace + Basic Oxygen Furnace w/ CO2 capture | C51: Part of 24.1 (Manufacture of basic iron and steel and of ferro-alloys) | D51: 45092 | E51: zotin | F51: Input data used in the IMAGE model, see also van Ruijven et al. (2016) and van Sluisveld et al. (2021). | G51: 2,3,4,5
F52: Additional comments, assumptions, and proxy choices made:
F53: Tbd.
F54: Qualitative evaluation of the data
F55: Tbd.
A57: [IMAGE] SR/BOF | B57: Smelting reduction + Basic Oxygen Furnace | C57: Part of 24.1 (Manufacture of basic iron and steel and of ferro-alloys) | D57: 45092 | E57: zotin | F57: Input data used in the IMAGE model, see also van Ruijven et al. (2016) and van Sluisveld et al. (2021). | G57: 2,3,4,5
F58: Additional comments, assumptions, and proxy choices made:
F59: Tbd.
F60: Qualitative evaluation of the data
F61: Tbd.
A63: [IMAGE] SR/BOF+CCS | B63: Smelting reduction + Basic Oxygen Furnace w/ CO2 capture | C63: Part of 24.1 (Manufacture of basic iron and steel and of ferro-alloys) | D63: 45092 | E63: zotin | F63: Input data used in the IMAGE model, see also van Ruijven et al. (2016) and van Sluisveld et al. (2021). | G63: 2,3,4,5
F64: Additional comments, assumptions, and proxy choices made:
F65: Tbd.
F66: Qualitative evaluation of the data
F67: Tbd.
A69: [IMAGE] DRI/EAF+CCS | B69: Direct Reduced Iron + Electric Arc Furnace w/ CO2 capture | C69: Part of 24.1 (Manufacture of basic iron and steel and of ferro-alloys) | D69: 45092 | E69: zotin | F69: Input data used in the IMAGE model, see also van Ruijven et al. (2016) and van Sluisveld et al. (2021). | G69: 2,3,4,5
F70: Additional comments, assumptions, and proxy choices made:
F71: Tbd.
F72: Qualitative evaluation of the data
F73: Tbd.
A75: [IMAGE] TGRBF/BOF | B75: Top Gas Recycling Blast Furnace + Basic Oxygen Furnace | C75: Part of 24.1 (Manufacture of basic iron and steel and of ferro-alloys) | D75: 45092 | E75: zotin | F75: Input data used in the IMAGE model, see also van Ruijven et al. (2016) and van Sluisveld et al. (2021). | G75: 2,3,4,5
F76: Additional comments, assumptions, and proxy choices made:
F77: Tbd.
F78: Qualitative evaluation of the data
F79: Tbd.
A81: [IMAGE] TGRBF BAT/BOF | B81: Top Gas Recycling Blast Furnace BAT + Basic Oxygen Furnace | C81: Part of 24.1 (Manufacture of basic iron and steel and of ferro-alloys) | D81: 45092 | E81: zotin | F81: Input data used in the IMAGE model, see also van Ruijven et al. (2016) and van Sluisveld et al. (2021). | G81: 2,3,4,5
F82: Additional comments, assumptions, and proxy choices made:
F83: Tbd.
F84: Qualitative evaluation of the data
F85: Tbd.
A87: [IMAGE] TGRBF BAT/BOF+CCS | B87: Top Gas Recycling Blast Furnace BAT + Basic Oxygen Furnace w/ CO2 capture | C87: Part of 24.1 (Manufacture of basic iron and steel and of ferro-alloys) | D87: 45092 | E87: zotin | F87: Input data used in the IMAGE model, see also van Ruijven et al. (2016) and van Sluisveld et al. (2021). | G87: 2,3,4,5
F88: Additional comments, assumptions, and proxy choices made:
F89: Tbd.
F90: Qualitative evaluation of the data
F91: Tbd.
A93: [IMAGE] H-DR/EAF | B93: Hydrogen Direct Reduced Iron + Electric Arc Furnace | C93: Part of 24.1 (Manufacture of basic iron and steel and of ferro-alloys) | D93: 45092 | E93: zotin | F93: Input data used in the IMAGE model, see also van Ruijven et al. (2016) and van Sluisveld et al. (2021). | G93: 2,3,4,5
F94: Additional comments, assumptions, and proxy choices made:
F95: Tbd.
F96: Qualitative evaluation of the data
F97: Tbd.
A99: [IMAGE] Electrowinning/EAF | B99: Electrowinning + Electric Arc Furnace | C99: Part of 24.1 (Manufacture of basic iron and steel and of ferro-alloys) | D99: 45092 | E99: zotin | F99: Input data used in the IMAGE model, see also van Ruijven et al. (2016) and van Sluisveld et al. (2021). | G99: 2,3,4,5
F100: Additional comments, assumptions, and proxy choices made:
F101: Tbd.
F102: Qualitative evaluation of the data
F103: Tbd.
A105: [Open-IDTD] BF/BOF | B105: BF/BOF | C105: Part of 24.1 (Manufacture of basic iron and steel and of ferro-alloys) | D105: 45124 | E105: zotin | F105: Reported in the Open Industrial Demand Technology Database, Lerede et al. (2021) | G105: 6, 7,8
F106: Additional comments, assumptions, and proxy choices made:
F107: Quoted from technology description in Lerede et al. (2021): 'The most used two-step production process for steel. The blast furnace reduces iron ore into pig iron, also called hot metal – the chief ingredient used to make the steel – in this case through oxidation of carbon and silicon of the pig iron in a basic oxygen furnace. Further processing in the basic oxygen furnace provides crude steel [1], [2].'
F108: Qualitative evaluation of the data
F109: Tbd.
A111: [Open-IDTD] DRI/EAF | C111: Part of 24.1 (Manufacture of basic iron and steel and of ferro-alloys) | D111: 45124 | E111: zotin | F111: Reported in the Open Industrial Demand Technology Database, Lerede et al. (2021) | G111: 6,9,10
F112: Additional comments, assumptions, and proxy choices made:
F113: Quoted from technology description in Lerede et al. (2021): 'Steel is produced starting from solid iron, derived from the direct reduction of iron ore, processed in an electric arc furnace [3]. In the direct reduction process, natural gas is used as fuel for the reduction of iron ore, and the produced steel has lower quality with respect to the BF-BOF product. Several technology options exist for the DRI steelmaking route, according to either the kind of employed reactor (shaft furnace, rotary kiln, rotary hearth furnace of fluidized bed reactor) or the type of iron ore feedstock (pellets and lump ore, or fines and concentrates) [4]. The most widely used process for direct reduction the Midrex shaft furnace technology.'
F114: Qualitative evaluation of the data
F115: Tbd.
A117: [Open-IDTD] Scrap | C117: Part of 24.1 (Manufacture of basic iron and steel and of ferro-alloys) | D117: 45124 | E117: zotin | F117: Reported in the Open Industrial Demand Technology Database, Lerede et al. (2021) | G117: 6
...

Sheet ref
B2: Dataset | D2: literature_id | G2: data source name/type/report | H2: authors | I2: title | J2: year | K2: journal_outlet_institution | L2: city | M2: DOI (for papers) and checksum (MD5) for datasets and scripts | N2: URL or link to document, name of document | O2: copyright | P2: archive location | Q2: notes
B3: 4_UPI_CIRCOMOD_D4.1_v1.0 | D3: 1 | G3: U.S. Life Cycle Inventory Database. (2012). National Renewable Energy Laboratory, 2012. Accessed 2018-09-05: https://www.lcacommons.gov/nrel/search | H3: Franklin Associates | I3: Data Details for limestone mining and lime production, Franklin Associates, 2004 | J3: 2004 | N3: https://www.lcacommons.gov/lca-collaboration/National_Renewable_Energy_Laboratory/USLCI/dataset/PROCESS/49e563d8-0cea-3f97-96b8-15787be48b91 | Q3: sample data
B4: 4_UPI_CIRCOMOD_D4.1_v1.0 | D4: 2 | G4: van Ruijven, B. J., van Vuuren, D. P., Boskaljon, W., Neelis, M. L., Saygin, D., & Patel, M. K. (2016). Long-term model-based projections of energy use and CO2 emissions from the global steel and cement industries. Resources, Conservation and Recycling, 112, 15–36. https://doi.org/10.1016/j.resconrec.2016.04.016 | H4: van Ruijven, B. J., van Vuuren, D. P., Boskaljon, W., Neelis, M. L., Saygin, D., & Patel, M. K. | I4: Long-term model-based projections of energy use and CO2 emissions from the global steel and cement industries | J4: 2016 | K4: Resources, Conservation and Recycling | M4: https://doi.org/10.1016/j.resconrec.2016.04.016
B5: 4_UPI_CIRCOMOD_D4.1_v1.0 | D5: 3 | H5: Roorda C, Neelis ML | I5: Inclusion of production, energy use and value added for steel, cement and paper in the TIMER energy demand module | J5: 2006 | K5: Netherlands Environment Assessment Agency | L5: Utrecht | N5: https://dspace.library.uu.nl/bitstream/handle/1874/21828/NWS-E-2006-179.pdf?sequence=1 | P5: No. NWS-E-2006-179
B6: 4_UPI_CIRCOMOD_D4.1_v1.0 | D6: 4 | G6: van Sluisveld, M. A. E., de Boer, H. S., Daioglou, V., Hof, A. F., & van Vuuren, D. P. (2021). A race to zero - Assessing the position of heavy industry in a global net-zero CO2 emissions context. Energy and Climate Change, 2(July), 100051. https://doi.org/10.1016/j.egycc.2021.100051 | H6: van Sluisveld, M. A. E., de Boer, H. S., Daioglou, V., Hof, A. F., & van Vuuren, D. P. | I6: A race to zero - Assessing the position of heavy industry in a global net-zero CO2 emissions context. https://doi.org/10.1016/j.egycc.2021.100051 | J6: 2021 | K6: Energy and Climate Change | M6: https://doi.org/10.1016/j.egycc.2021.100051
B7: 4_UPI_CIRCOMOD_D4.1_v1.0 | D7: 5 | G7: ETP Clean Energy Technology Guide | H7: IEA | J7: 2022 | K7: - | L7: - | M7: - | N7: https://www.iea.org/data-and-statistics/data-tools/etp-clean-energy-technology-guide
B8: 4_UPI_CIRCOMOD_D4.1_v1.0 | D8: 6 | H8: D. Lerede a, C. Bustreo b, F. Gracceva c, M. Saccone a, L. Savoldi | I8: Techno-economic and environmental characterization of industrial technologies for transparent bottom-up energy modeling | J8: 2021 | K8: Renewable and Sustainable Energy Reviews | M8: 10.1016/j.rser.2021.110742 | N8: https://www.sciencedirect.com/science/article/pii/S1364032121000381
B9: 4_UPI_CIRCOMOD_D4.1_v1.0 | D9: 7 | G9: Online | H9: AISI | I9: Steel Production | J9: 2020 | M9: - | N9: https://www.steel.org/steel-technology/steel-production
B10: 4_UPI_CIRCOMOD_D4.1_v1.0 | D10: 8 | G10: Book | H10: P. Cavaliere | I10: Clean Ironmaking and Steelmaking Processes - Efficient Technologies for Greenhouse Emissions Abatement | J10: 2019 | K10: Springer International Publishing | M10: -
B11: 4_UPI_CIRCOMOD_D4.1_v1.0 | D11: 9 | G11: Report | H11: American Iron and Steel Institute | I11: Technology Roadmap Research Program | J11: 2010 | N11: -
B12: 4_UPI_CIRCOMOD_D4.1_v1.0 | D12: 10 | G12: Report | H12: European Commission | I12: Best Available Techniques Reference Document on the Production of Iron and Steel | J12: 2013 | K12: Publications Office of the European Union | L12: Luxembourg | M12: -
B13: 4_UPI_CIRCOMOD_D4.1_v1.0 | D13: 11 | G13: Journal Article | H13: R. Steffen | I13: Direct reduction and smelting reduction – an overview | J13: 1989 | K13: Steel Research | M13: -
B14: 4_UPI_CIRCOMOD_D4.1_v1.0 | D14: 12 | G14: Online | H14: Siemens | I14: Automation technology | J14: 2020 | M14: - | N14: https://new.siemens.com/global/en/company/about/history/technology/drive-and-automation-technology/automation-technology.html
B15: 4_UPI_CIRCOMOD_D4.1_v1.0 | D15: 13 | G15: Online | H15: B. B. Agrawal and A. S. Mathur | I15: New Ironmaking Processes: Relevance to India | J15: 2020 | M15: - | N15: http://www.iim-delhi.com/upload_events/01NewIronmakingProcessRelevanceIndia_RDCIS.pdf
B16: 4_UPI_CIRCOMOD_D4.1_v1.0 | D16: 14 | G16: Report | H16: IEA | I16: Energy Technology Perspectives 2017 | J16: 2017 | K16: IEA Publications | L16: Paris | M16: -
B17: 4_UPI_CIRCOMOD_D4.1_v1.0 | D17: 15 | G17: Online | H17: Tata Steel | I17: HIsarna factsheet | J17: 2020 | M17: - | N17: https://www.tatasteeleurope.com/static_files/Downloads/Corporate/About%20us/hisarna%20factsheet.pdf
B18: 4_UPI_CIRCOMOD_D4.1_v1.0 | D18: 16 | G18: Report | H18: IEA, UNIDO | I18: Technology Roadmap - Carbon Capture and Storage in Industrial Applications | J18: 2011 | K18: IEA Publications | L18: Paris | M18: -
B19: 4_UPI_CIRCOMOD_D4.1_v1.0 | D19: 17 | G19: Report | H19: H. Croezen and M. Korteland | I19: A long-term view of CO2 efficient manufacturing in the European region | J19: 2010 | N19: -
B20: 4_UPI_CIRCOMOD_D4.1_v1.0 | D20: 18 | G20: Journal Article | H20: D. Nuber, H. Eichberger, B. Rollinger | I20: Circored fine ore direct reduction | J20: 2006 | K20: Millenium Steel | M20: -
B21: 4_UPI_CIRCOMOD_D4.1_v1.0 | D21: 19 | G21: Report | H21: J. P. Birat | I21: ULCOS program: status and progress | J21: 2010 | L21: Brussels | M21: -
B22: 4_UPI_CIRCOMOD_D4.1_v1.0 | D22: 20 | G22: Report | H22: R. Remus, M. A. Aguado-Monsonet, S. Roudier, L. Delgado Sancho | I22: Best Available Techniques (BAT) Reference Document for Iron and Steel Production | J22: 2013 | K22: Publications Office of the European Union | L22: Luxembourg | M22: -
B23: 4_UPI_CIRCOMOD_D4.1_v1.0 | D23: 21 | G23: Report | H23: S. A. Singerling, C. A. Tuck, G. M. Bedinger, L. A. Corathers, P. H. Kuck, J. F. Papp, D. A. Polyak, E. K. Schnebele, K. B. Shedd | I23: Geological Survey Minerals Yearbook - Ferroalloys | J23: 2015 | K23: USGS | L23: Reston, USA | M23: -
B24: 4_UPI_CIRCOMOD_D4.1_v1.0 | D24: 22 | G24: Journal Article | H24: P. Mandin, R. Wüthrich, H. Roustan | I24: Industrial Aluminium Production: the Hall-Heroult Process Modelling | J24: 2009 | K24: ECS Transactions | M24: -
B25: 4_UPI_CIRCOMOD_D4.1_v1.0 | D25: 23 | G25: Report | H25: J. A. Moya, A. Boulamati, S. Slingerlan, R. van der Veen, M. Gancheva, K. M. Rademaekers, J. J. P. Kuenen, A. J. H. Visschedijk | I25: Energy Efficiency and GHG Emissions: Prospective Scenarios for the Aluminum Industry | J25: 2015 | K25: Publications Office of the European Union | L25: Luxembourg | M25: -
B26: 4_UPI_CIRCOMOD_D4.1_v1.0 | D26: 24 | G26: Journal Article | H26: A. Boulamanti and J. A. Moya | I26: Production costs of the non-ferrous metals in the EU and other countries: Copper and zinc | J26: 2016 | K26: Resources Policy | M26: -
B27: 4_UPI_CIRCOMOD_D4.1_v1.0 | D27: 25 | G27: Report | H27: G. Cusano, M. R. Gonzalo, F. Farrell, R. Remus, S. Roudier, L. Delgado Sancho | I27: Best Available Techniques (BAT) Reference Document for the Non-Ferrous Metals Industries | J27: 2017 | K27: Publication Office of the European Union | L27: Luxembourg | M27: -
B28: 4_UPI_CIRCOMOD_D4.1_v1.0 | D28: 26 | G28: Report | H28: IEA | I28: Tracking Industrial Energy Efficiency and CO2 Emissions | J28: 2007 | K28: IEA Publications | L28: Paris, France | M28: -
B29: 4_UPI_CIRCOMOD_D4.1_v1.0 | D29: 27 | G29: Book | H29: A. Valero Capilla | I29: Thanatia: the destiny of Earth's mineral resources | J29: 2014 | K29: World Scientific Publishing Co. Pde. Ltd. | L29: Singapore | M29: -
B30: 4_UPI_CIRCOMOD_D4.1_v1.0 | D30: 28 | G30: Online | H30: International tin | I30: Sustainable production | J30: 2020 | M30: - | N30: https://www.internationaltin.org/sustainable-production/
B31: 4_UPI_CIRCOMOD_D4.1_v1.0 | D31: 29 | G31: Journal Article | H31: G. Z. Chen, D. J. Fray, T. W. Farthing | I31: Direct Electrochemical Reduction of Titanium Dioxide to Titanium in Molten Calcium Chloride | J31: 2000 | K31: Nature | M31: DOI:10.1038/35030069
B32: 4_UPI_CIRCOMOD_D4.1_v1.0 | D32: 30 | G32: Online | H32: ITER | I32: Magnets | J32: 2020 | M32: - | N32: https://www.iter.org/mach/Magnets
B33: 4_UPI_CIRCOMOD_D4.1_v1.0 | D33: 31 | G33: Journal Article | H33: N. A. Madlool, R. Saidur, M. S. Hossain, N. Rahim | I33: A critical review on energy use and savings in the cement industries | J33: 2011 | K33: Renewable and Sustainable Energy Reviews | M33: -
B34: 4_UPI_CIRCOMOD_D4.1_v1.0 | D34: 32 | G34: Report | H34: ETSAP | I34: Technology Brief - Cement Production | J34: 2010 | N34: -
B35: 4_UPI_CIRCOMOD_D4.1_v1.0 | D35: 33 | G35: Report | H35: IEAGHG | I35: Deployment of CCS in the cement industry | J35: 2013 | N35: -
B36: 4_UPI_CIRCOMOD_D4.1_v1.0 | D36: 34 | G36: Online | H36: Cembureau | I36: Clinker Substitution | J36: 2020 | M36: - | N36: https://lowcarboneconomy.cembureau.eu/5-parallel-routes/resource-efficiency/clinker-substitution/
B37: 4_UPI_CIRCOMOD_D4.1_v1.0 | D37: 35 | G37: Report | H37: U.S. Environmental Protection Agency | I37: Lime Manufacturing | J37: - | N37: -
B38: 4_UPI_CIRCOMOD_D4.1_v1.0 | D38: 36 | G38: Journal Article | H38: T. Ren, M. Patel, K. Blok | I38: Olefins from conventional and heavy feedstocks: Energy use in steam cracking and alternative processes | J38: 2006 | K38: Energy | M38: -
B39: 4_UPI_CIRCOMOD_D4.1_v1.0 | D39: 37 | G39: Report | H39: IEA | I39: The Future of Petrochemicals - Towards more sustainable plastics and fertilizers | J39: 2018 | K39: IEA Publications | L39: Paris | M39: -
B40: 4_UPI_CIRCOMOD_D4.1_v1.0 | D40: 38 | G40: Book | H40: Z. Salameh | I40: Renewable Energy System Design | J40: 2014 | K40: Elsevier | M40: -
B41: 4_UPI_CIRCOMOD_D4.1_v1.0 | D41: 39 | G41: Report | H41: European Commission | I41: Reference Document on Best Available Techniques for the Manufacture of Large Volume Inorganic Chemicals - Ammonia, Acids and Fertilisers | J41: 2007 | N41: -
B42: 4_UPI_CIRCOMOD_D4.1_v1.0 | D42: 40 | G42: Online | H42: OGCI | I42: OGCI Climate Investments, the Oil and Gas Climate Initiative’s investment arm, announces a new investment in carbon capture and sequestration (CCS) project to create the world’s first ammonia produced with near zero carbon footprint | J42: 2019 | M42: - | N42: https://oilandgasclimateinitiative.com/ogci-climate-investments-announces-a-new-investment-in-wabash-valley-resources-carbon-capture-and-sequestration-project/
B43: 4_UPI_CIRCOMOD_D4.1_v1.0 | D43: 41 | G43: Report | H43: T. Brinkmann, G. G. Santonja, F. Schorcht, R. Serge, L. Delgado Sancho | I43: Best Available Techniques (BAT) Reference Document for the Production of Chlor-alkali | J43: 2014 | K43: Publications Office of the European Union | L43: Luxembourg | M43: -
B44: 4_UPI_CIRCOMOD_D4.1_v1.0 | D44: 42 | G44: Book Section | H44: P. Bajpai | I44: Pulp and Paper Production Processes and Energy Overview | J44: 2016 | K44: Elsevier | M44: In: Pulp and Paper Industry, pp. 15-49
B45: 4_UPI_CIRCOMOD_D4.1_v1.0 | D45: 43 | G45: Report | H45: Jaccard M. and Willis Enterprises Associates | I45: Energy Conservation Potential in Six Canadian Industries | J45: 1996 | N45: -
B46: 4_UPI_CIRCOMOD_D4.1_v1.0 | D46: 44 | G46: Report | H46: US Department of Energy | I46: Energy and environmental profile of the U.S. pulp and paper industry | J46: 2005 | N46: -
B47: 4_UPI_CIRCOMOD_D4.1_v1.0 | D47: 45 | G47: Report | H47: ETSAP | I47: Technology brief, Pulp and Paper Industry | J47: 2015 | N47: -
B48: 4_UPI_CIRCOMOD_D4.1_v1.0 | D48: 46 | G48: Report | H48: M. Suhr, G. Klein, I. Kourti, M. Rodrigo Gonzalo, G. Giner Santonja, S. Roudier, L. Delgado Sancho | I48: Best Available Techniques (BAT) Reference Document for the Production of Paper, Pulp and Board | J48: 2015 | K48: Publications Office of the European Commission | L48: Luxembourg | M48: -
B49: 4_UPI_CIRCOMOD_D4.1_v1.0 | D49: 47 | G49: Dataset | H49: Nijs, Wouter; Ruiz, Pablo | J49: 2019 | K49: European Commission, Joint Research Centre (JRC) | N49: http://data.europa.eu/89h/8141a398-41a8-42fa-81a4-5b825a51761b
B50: 4_UPI_CIRCOMOD_D4.1_v1.0 | D50: 48 | G50: Report | H50: Keys et al. | I50: Decarbonisation options for the Dutch steel industry | J50: 2019 | K50: PBL and TNO Energy Transition
B51: 4_UPI_CIRCOMOD_D4.1_v1.0 | D51: 49 | G51: Report | H51: R. Remus, M. A. Aguado Monsonet, S. Roudier, L. Delgado Sancho | I51: Best Available Techniques (BAT) Reference Document for Iron and Steel Production | J51: 2013 | K51: Publications Office of the European Union | L51: Luxembourg
B52: 4_UPI_CIRCOMOD_D4.1_v1.0 | D52: 50 | G52: Online | I52: CBS statline energy balance | J52: 2017 | N52: https://opendata.cbs.nl/statline/#/CBS/nl/dataset/83989NED/table?dl=2058D
B53: 4_UPI_CIRCOMOD_D4.1_v1.0 | D53: 51 | G53: Report | H53: Worrell et al. | I53: World Best Practice Energy Intensity Values for Selected Industrial Sectors | J53: 2007 | N53: https://escholarship.org/content/qt77n9d4sp/qt77n9d4sp.pdf
B54: 4_UPI_CIRCOMOD_D4.1_v1.0 | D54: 52 | G54: Online | H54: Vattenfall | I54: IJmond | N54: https://powerplants.vattenfall.com/ijmond
B55: 4_UPI_CIRCOMOD_D4.1_v1.0 | D55: 53 | G55: Report | H55: Gérard Danloy, Jan van der Stel, Peter Schmöle | I55: Heat and mass balances in the ULCOS Blast Furnace | J55: 2008
B56: 4_UPI_CIRCOMOD_D4.1_v1.0 | D56: 54 | G56: Report | H56: Global CCS Institute | I56: CCS for the Steel sector | J56: 2010
B57: 4_UPI_CIRCOMOD_D4.1_v1.0 | D57: 55 | G57: Report | H57: LKAB, Global CCS Institute | I57: ULCORED Direct Reduction Concept for ULCOS - a brief introduction, CCS for the Steel sector | J57: 2013
B58: 4_UPI_CIRCOMOD_D4.1_v1.0 | D58: 56 | G58: Report | H58: Bert Daniels | I58: Transition Paths towards f_gases Emission Reduction in the Steel Industry | J58: 2002
B59: 4_UPI_CIRCOMOD_D4.1_v1.0 | D59: 57 | G59: Report | H59: Marc Hölling | I59: Direct Reduction: Transition from Natural Gas to Hydrogen? | J59: 2018
B60: 4_UPI_CIRCOMOD_D4.1_v1.0 | D60: 58 | G60: Report | H60: Aldel | I60: Informatiepakket voor de aanvraag voor de vergunning wet milieubeheer, voor Aluminium Delfzijl BV | J60: 2007 | L60: Province of Groningen
B61: 4_UPI_CIRCOMOD_D4.1_v1.0 | D61: 59 | G61: Report | H61: Aldel | I61: (Ontwerp) vergunning wet milieubeheer – verleend aan Aluminium Delfzijl B.V. (Aldel), een aluminiumfabriek met gieterij | J61: 2008 | L61: Province of Groningen
B62: 4_UPI_CIRCOMOD_D4.1_v1.0 | D62: 60 | G62: Report | H62: Aldel, EAA, IPCC | I62: Environmental profile report – Life-Cycle inventory data for aluminium production and transformation processes in Europe, Global Warming Potential Values | J62: 2007, 2018, 2016 | K62: European Aluminium Association, Intergovernmental Panel on Climate Change
B63: 4_UPI_CIRCOMOD_D4.1_v1.0 | D63: 61 | G63: Report | H63: U.S. Department of Energy's Office of Energy Efficiency and Renewable Energy | I63: U.S. Energy Requirements for Aluminium Production–Historical Perspective, Theoretical limits and Current Practices | J63: 2007
B64: 4_UPI_CIRCOMOD_D4.1_v1.0 | D64: 62 | G64: Journal Article | H64: Obaidat M, Al-Ghandoor A, Phelan P, Villalobos R, Alkhalidi A | I64: Energy and Exergy Analyses of Different Aluminum Reduction Technologies | J64: 2018 | K64: sustainability | M64: 10.3390/su10041216
B65: 4_UPI_CIRCOMOD_D4.1_v1.0 | D65: 63 | G65: Report | H65: Aluchemie, Century | I65: Aluchemie–Maatschappelijk verslag 2012, Century Aluminum Vlissingen operations–Sociaal Jaarverslag 2017 | J65: 2012, 2017
B66: 4_UPI_CIRCOMOD_D4.1_v1.0 | D66: 64 | G66: Report | H66: Aluchemie, Century | I66: Aluchemie–Maatschappelijk verslag 2012, Personal communication with R. Quak | J66: 2012, 2018
B67: 4_UPI_CIRCOMOD_D4.1_v1.0 | D67: 65 | G67: Report | H67: Aluchemie, Century, NEa | I67: Aluchemie–Maatschappelijk verslag 2012, Century Aluminum Vlissingen operations–Sociaal Jaarverslag 2017, Emissiecijfers industrie 2013-2017 | J67: 2012, 2017, 2018 | K67: NEa (Netherlands Emission Authority)
B68: 4_UPI_CIRCOMOD_D4.1_v1.0 | D68: 66 | G68: Report | H68: E-MAX, Zalco | I68: Personal communication with C. Kampen, Personal communication with J. van Wijck | J68: 2018
B69: 4_UPI_CIRCOMOD_D4.1_v1.0 | D69: 67 | G69: Report | H69: ENCI | I69: ENCI Rotterdam / IJmuiden Veiligheid en milieu - Feiten & cijfers 2017 | J69: 2017 | L69: Rotterdam
B70: 4_UPI_CIRCOMOD_D4.1_v1.0 | D70: 68 | G70: Report | H70: ECRA | I70: Development of State of the Art Techniques in Cement Manufacturing: Trying to Look Ahead | J70: 2017 | M70: A-2016/2305 CSI/ECRA-Technology Papers
B71: 4_UPI_CIRCOMOD_D4.1_v1.0 | D71: 69 | G71: Report | H71: EHPA | I71: Key Facts on Heat Pumps | J71: 2020 | N71: https://www.ehpa.org/technology/key-facts-on-heat-pumps/
B72: 4_UPI_CIRCOMOD_D4.1_v1.0 | D72: 70 | G72: Report | H72: IFC | I72: IMPROVING THERMAL AND ELECTRIC ENERGY EFFICIENCY AT CEMENT PLANTS: INTERNATIONAL BEST PRACTICE | J72: 2020
B73: 4_UPI_CIRCOMOD_D4.1_v1.0 | D73: 71 | G73: Journal Article | H73: Daioglou, Vassilis; Andre P.C. Faaij; Deger Saygin; Martin K. Patel; Birka Wicke; Detlef P. Van Vuuren | I73: Energy Demand and Emissions of the Non-Energy Sector | J73: 2014 | K73: Energy and Environmental Science | M73: https://doi.org/10.1039/c3ee42667j
B74: 4_UPI_CIRCOMOD_D4.1_v1.0 | D74: 72 | G74: Journal Article | H74: Nadine Rötzer and Mario Schmidt | I74: Historical, Current, and Future Energy Demand from Global Copper Production and Its Impact on Climate Change | J74: 2020 | K74: Resources | L74: Pforzheim, Germany | M74: doi:10.3390/resources9040044 | N74: https://www.mdpi.com/2079-9276/9/4/44
B75: 4_UPI_CIRCOMOD_D4.1_v1.0 | D75: 73 | G75: Journal Article | H75: Wernet, G., Bauer, C., Steubing, B., Reinhard, J., Moreno-Ruiz, E., and Weidema, B | I75: The ecoinvent database version 3 (part I): overview and methodology | J75: 2016 | K75: The International Journal of Life Cycle Assessment | M75: https://doi.org/10.1007/s11367-016-1087-8 | N75: http://link.springer.com/10.1007/s11367-016-1087-8
B76: 4_UPI_CIRCOMOD_D4.1_v1.0 | D76: 74 | G76: Book | H76: Mark E. Schlesinger, Kathryn C. Sole, William G. Davenport, Gerardo R.F. Alvear Flores | I76: Extractive Metallurgy of Copper, Sixth Edition | J76: 2021 | K76: Elsevier | M76: https://doi.org/10.1016/C2019-0-03265-7 | N76: https://doi.org/10.1016/C2019-0-03265-7
B77: 4_UPI_CIRCOMOD_D4.1_v1.0 | D77: 75 | G77: Journal Article | H77: Coursol, Pascal & Mackey, P. & Kapusta, Joel & Cardona Valencia, Nubia | I77: Energy Consumption in Copper Smelting: A New Asian Horse in the Race | J77: 2015 | K77: JOM: the journal of the Minerals, Metals & Materials Society | M77: 10.1007/s11837-015-1380-1
B78: 4_UPI_CIRCOMOD_D4.1_v1.0 | D78: 76 | G78: Report | H78: International Copper Study Group | I78: The World Copper Factbook 2022 | J78: 2022 | N78: https://icsg.org/copper-factbook/
B79: 4_UPI_CIRCOMOD_D4.1_v1.0 | D79: 77 | G79: Report | H79: Moats, M., Filzwieser, A., Wang, S., Davenport, W. G., Siegmund, A., & Robinson, T. | I79: Global Survey of Copper Electrorefining: 2019 World Tankhouse Operating Data | J79: 2019 | N79: https://store.cim.org/en/global-survey-of-copper-electrorefining-2019-world-tankhouse-operating-data
B80: 4_UPI_CIRCOMOD_D4.1_v1.0 | D80: 78 | G80: Journal Article | H80: Yi Zhang, Yijun Ji, He Xu, Yiting Yang, Lili Tian | I80: Life cycle assessment of valuable metal extraction from copper pyrometallurgical solid waste | J80: 2023 | K80: Resources, Conservation and Recycling | M80: 10.1016/j.resconrec.2023.106875 | N80: https://doi.org/10.1016/j.resconrec.2023.106875
B81: 4_UPI_CIRCOMOD_D4.1_v1.0 | D81: 79 | G81: Journal Article | H81: Wenbiao Zhang, Zehong Li, Suocheng Dong, Peng Qian, Shufeng Ye, Shuhan Hu, Bing Xia, Chunying Wang | I81: Analyzing the environmental impact of copper-based mixed waste recycling-a LCA case study in China | J81: 2021 | K81: Journal of Cleaner Production | M81: 10.1016/j.jclepro.2020.125256 | N81: https://doi.org/10.1016/j.jclepro.2020.125256
B82: 4_UPI_CIRCOMOD_D4.1_v1.0 | D82: 80 | G82: Journal Article | H82: Qisthi, Aulia & Sembada, Agung & Tse, Kwong Ming & Rhamdhani, M | I82: Assessment of Mass and Energy Balance of Waste Printed Circuit Board Recycling through Hydrogen Reduction in Black Copper Smelting Process | J82: 2023 | K82: Processes | M82: 10.3390/pr11051506 | N82: https://doi.org/10.3390/pr11051506
B83: 4_UPI_CIRCOMOD_D4.1_v1.0 | D83: 81 | G83: Journal Article | H83: Goonan, T.G. | I83: Flows of Selected Materials Associated with World Copper Smelting; Open-File Report 2004-1395 | J83: 2004 | K83: U.S. Geological Survey | N83: https://pubs.usgs.gov/of/2004/1395/2004-1395.pdf
B84: 4_UPI_CIRCOMOD_D4.1_v1.0 | D84: 82 | G84: Journal Article | H84: Becci, Alessandro & Amato, Alessia & Fonti, Viviana & Karaj, Dafina & Beolchini, Francesca | I84: An innovative biotechnology for metal recovery from printed circuit boards | J84: 2020 | K84: Resources, Conservation and Recycling | M84: 10.1016/j.resconrec.2019.104549 | N84: https://doi.org/10.1016/j.resconrec.2019.104549
B85: 4_UPI_CIRCOMOD_D4.1_v1.0 | D85: 83 | G85: Journal Article | H85: Ippolito, N.M., Innocenzi, V., De Michelis, I., Medici, F., Vegliò, F | I85: Rare earth elements recovery from fluorescent lamps: a new thermal pretreatment to improve the efficiency of the hydrometallurgical process | J85: 2017 | K85: J. Clean. Prod | M85: 10.1016/j.jclepro.2017.03.195 | N85: https://doi.org/10.1016/j.jclepro.2017.03.195
B86: 4_UPI_CIRCOMOD_D4.1_v1.0 | D86: 84 | G86: Report | H86: Oliveira & Xavier Silva | I86: Decarbonisation options for the Dutch asphalt industr | J86: 2022 | K86: PBL report | N86: https://www.pbl.nl/sites/default/files/downloads/pbl-2022-decarbonisation-options-for-the-dutch-asphalt-industry_4791.pdf
B87: 4_UPI_CIRCOMOD_D4.1_v1.0 | D87: 85 | G87: Journal Article | H87: Hanein, Theodore, Karl-Christian Thienel, Franco Zunino, Alastair T. M. Marsh, Matthias Maier, Bin Wang, Mariana Canut, et al. | I87: Clay Calcination Technology: State-of-the-Art Review by the RILEM TC 282-CCL | J87: 2021 | K87: Materials and Structures | M87: 10.1617/s11527-021-01807-6 | N87: https://doi.org/10.1617/s11527-021-01807-6
B88: 4_UPI_CIRCOMOD_D4.1_v1.0 | D88: 86 | G88: Journal Article | H88: Cancio Díaz, Yudiesky, Sofia Sánchez Berriel, Urs Heierli, Aurélie R. Favier, Inocencio R. Sánchez Machado, Karen L. Scrivener, José Fernando Martirena Hernández, and Guillaume Habert. | I88: Limestone Calcined Clay Cement as a Low-Carbon Solution to Meet Expanding Cement Demand in Emerging Economies. | J88: 2017 | K88: Development Engineering | M88: 10.1016/j.deveng.2017.06.001 | N88: https://doi.org/10.1016/j.deveng.2017.06.001
B89: 4_UPI_CIRCOMOD_D4.1_v1.0 | D89: 87 | G89: Journal Article | H89: Sánchez Berriel, S., A. Favier, E. Rosa Domínguez, I. R. Sánchez Machado, U. Heierli, K. Scrivener, F. Martirena Hernández, and G. Habert. | I89: Assessing the Environmental and Economic Potential of Limestone Calcined Clay Cement in Cuba | J89: 2016 | K89: Journal of Cleaner Production 124 (June): 361–69. | M89: 10.1016/j.jclepro.2016.02.125 | N89: https://doi.org/10.1016/j.jclepro.2016.02.125
B90: 4_UPI_CIRCOMOD_D4.1_v1.0 | D90: 88 | G90: Journal Article | H90: Martinez, Daniela M., Arpad Horvath, and Paulo J. M. Monteiro. | I90: Comparative Environmental Assessment of Limestone Calcined Clay Cements and Typical Blended Cements | J90: 2023 | K90: Environmental Research Communications 5 (5): 055002. | M90: 10.1088/2515-7620/acccd8 | N90: https://doi.org/10.1088/2515-7620/acccd8
B91: 4_UPI_CIRCOMOD_D4.1_v1.0 | D91: 89 | G91: Journal Article | H91: Shanks, W, CF Dunant, MP Drewniok, RC Lupton, A Serrenho, and JM Allwood. | I91: How Much Cement Can We Do without? Lessons from Cement Material Flows in the UK | J91: 2019 | K91: RESOURCES CONSERVATION AND RECYCLING 141 (February): 441–54. | M91: 10.1016/j.resconrec.2018.11.002 | N91: https://doi.org/10.1016/j.resconrec.2018.11.002
B92: 4_UPI_CIRCOMOD_D4.1_v1.0 | D92: 90 | G92: Journal Article | H92: Wang, Wei, Di Jiang, Dingjiang Chen, Zengbo Chen, Wenji Zhou, and Bing Zhu. | I92: A Material Flow Analysis (MFA)-Based Potential Analysis of Eco-Efficiency Indicators of China’s Cement and Cement-Based Materials Industry | J92: 2016 | K92: Journal of Cleaner Production 112 (January): 787–96. | M92: 10.1016/j.jclepro.2015.06.103 | N92: https://doi.org/10.1016/j.jclepro.2015.06.103
B93: 4_UPI_CIRCOMOD_D4.1_v1.0 | D93: 91 | G93: Journal Article | H93: Zuberi, M.J.S., Hasanbeigi, A. & Morrow, W. | I93: Techno-economic evaluation of industrial heat pump applications in US pulp and paper, textile, and automotive industries | J93: 2023 | K93: Energy Efficiency | M93: 10.1007/s12053-023-10089-6 | N93: https://doi.org/10.1007/s12053-023-10089-6
B94: 4_UPI_CIRCOMOD_D4.1_v1.0 | D94: 92 | G94: Journal Article | H94: Meng et al. | I94: Planet-compatible pathways for transitioning the chemical industry | J94: 2023 | K94: PNAS | M94: DOI 10.1073/pnas.2218294120 | N94: DOI 10.1073/pnas.2218294120
B95: 4_UPI_CIRCOMOD_D4.1_v1.0 | D95: 93 | G95: Online | I95: Energy content of biofuel | J95: 2023 | N95: https://en.wikipedia.org/wiki/Energy_content_of_biofuel
B96: 4_UPI_CIRCOMOD_D4.1_v1.0 | D96: 94 | G96: Online | H96: ogj.com | I96: Contaminants key to refinery offgas treatment unit design | J96: 2008 | N96: https://www.ogj.com/refining-processing/gas-processing/article/17217421/contaminants-key-to-refinery-offgas-treatment-unit-design
B97: 4_UPI_CIRCOMOD_D4.1_v1.0 | D97: 95 | G97: Dataset | H97: ecoinvent | I97: ecoinvent life cycle database version 3.8, via openLCA | J97: 2022 | L97: Zürich, Switzerland | O97: © ecoinvent
B98: 4_UPI_CIRCOMOD_D4.1_v1.0 | D98: 96 | G98: Journal Article | H98: Russo et al. | I98: Exergy-Based Assessment of Polymers Production and Recycling: An Application to the Automotive Sector | J98: 2021 | K98: Energies 2021, 14, 363. | N98: https://doi.org/10.3390/en14020363
B99: 4_UPI_CIRCOMOD_D4.1_v1.0 | D99: 97 | G99: Working paper | H99: Rüter and Diederichs | I99: Ökobilanz-Basisdaten für Bauprodukte aus Holz | J99: 2012 | K99: Working paper / Arbeitsbericht aus dem Institut für Holztechnologie und Holzbiologie Nr. 2012/1
B100: 4_UPI_CIRCOMOD_D4.1_v1.0 | D100: 98 | G100: Report | H100: World Steel | I100: World Steel in Figures 2018 | J100: 2018 | N100: https://www.worldsteel.org/en/dam/jcr:7eb5b4b0-2d1d-49d8-b580-a8ed74e67436/
B101: 4_UPI_CIRCOMOD_D4.1_v1.0 | D101: 99 | G101: Report | H101: Agora Energiewende | I101: Breakthrough Strategies for Climate-Neutral Industry in Europe: Policy and Technology Pathways for Raising EU Climate Ambition | J101: 2021 | N101: https://www.agora-energiewende.org/fileadmin/Projekte/2020/2020_10_Clean_Industry_Package/A-EW_208_Strategies-Climate-Neutral-Industry-EU_Study_WEB.pdf
...
